Workbook

Sheet Sheet1
A2: Season | B2: Team | C2: Level | D2: Age | E2: G | F2: PA | G2: HR | H2: R | I2: RBI | J2: SB | K2: BB% | L2: K% | M2: ISO | N2: BABIP | O2: AVG | P2: OBP | Q2: SLG | R2: wOBA | S2: xwOBA | T2: wRC+
A3: 2023 | B3: DET | C3: A+ | D3: 23 | E3: 45 | F3: 198 | G3: 6 | H3: 36 | I3: 29 | J3: 8 | K3: 0.086 | L3: 0.283 | M3: 0.147 | N3: 0.388 | O3: 0.288 | P3: 0.355 | Q3: 0.435 | R3: 0.363 | T3: 130
A4: 2023 | B4: DET | C4: AA | D4: 23 | E4: 55 | F4: 214 | G4: 7 | H4: 37 | I4: 19 | J4: 11 | K4: 0.145 | L4: 0.388 | M4: 0.191 | N4: 0.3 | O4: 0.191 | P4: 0.318 | Q4: 0.382 | R4: 0.321 | T4: 97
B6: Weighted | F6: =SUM(F3:F4) -> 412 | K6: =SUM((K3*$F$3)+(K4*$F$4))/412 -> 0.11664563 | L6: =SUM((L3*$F$3)+(L4*$F$4))/412 -> 0.33753883 | M6: =SUM((M3*$F$3)+(M4*$F$4))/412 -> 0.16985437 | N6: =SUM((N3*$F$3)+(N4*$F$4))/412 -> 0.34229126 | O6: =SUM((O3*$F$3)+(O4*$F$4))/412 -> 0.2376165 | P6: =SUM((P3*$F$3)+(P4*$F$4))/412 -> 0.33578155 | Q6: =SUM((Q3*$F$3)+(Q4*$F$4))/412 -> 0.40747087 | R6: =SUM((R3*$F$3)+(R4*$F$4))/412 -> 0.34118447 | T6: =SUM((T3*$F$3)+(T4*$F$4))/412 -> 112.85922
B8: A | C8: 1
B9: A+ | C9: 2
B10: AA | C10: 3
B11: AAA | C11: 4

Sheet Debut Class
A1: Year | B1: PlayerID | C1: Name | D1: Team | E1: G | F1: PA | G1: HR | H1: R | I1: RBI | J1: SB | K1: BB% | L1: K% | M1: ISO | N1: BABIP | O1: AVG | P1: OBP | Q1: SLG | R1: wOBA | S1: xwOBA | T1: wRC+ | U1: BsR | V1: Off | W1: Def | X1: WAR
A2: 2023 | B2: =_xlfn.XLOOKUP(C2,ID!$J$2:$J$3825,ID!$I$2:$I$3825,"n/a",0,1) -> 25878 | C2: Corbin Carroll | D2: ARI | E2: 155 | F2: 645 | G2: 25 | H2: 116 | I2: 76 | J2: 54 | K2: 0.088 | L2: 0.194 | M2: 0.221 | N2: 0.325 | O2: 0.285 | P2: 0.362 | Q2: 0.506 | R2: 0.37 | S2: 0.345 | T2: 133 | U2: 12.3 | V2: 38.3 | W2: -6.6 | X2: 5.3
A3: 2023 | B3: =_xlfn.XLOOKUP(C3,ID!$J$2:$J$3825,ID!$I$2:$I$3825,"n/a",0,1) -> 26289 | C3: Gunnar Henderson | D3: BAL | E3: 150 | F3: 622 | G3: 28 | H3: 100 | I3: 82 | J3: 10 | K3: 0.09 | L3: 0.256 | M3: 0.234 | N3: 0.306 | O3: 0.255 | P3: 0.325 | Q3: 0.489 | R3: 0.346 | S3: 0.346 | T3: 122 | U3: 5.8 | V3: 22.3 | W3: 3.2 | X3: 4.7
A4: 2023 | B4: =_xlfn.XLOOKUP(C4,ID!$J$2:$J$3825,ID!$I$2:$I$3825,"n/a",0,1) -> 24770 | C4: James Outman | D4: LAD | E4: 151 | F4: 567 | G4: 23 | H4: 86 | I4: 70 | J4: 16 | K4: 0.12 | L4: 0.319 | M4: 0.188 | N4: 0.343 | O4: 0.248 | P4: 0.353 | Q4: 0.437 | R4: 0.344 | S4: 0.324 | T4: 117 | U4: 3.4 | V4: 15.1 | W4: 4.7 | X4: 3.9
A5: 2023 | B5: =_xlfn.XLOOKUP(C5,ID!$J$2:$J$3825,ID!$I$2:$I$3825,"n/a",0,1) -> 20529 | C5: Nolan Jones | D5: COL | E5: 106 | F5: 424 | G5: 20 | H5: 60 | I5: 62 | J5: 20 | K5: 0.125 | L5: 0.297 | M5: 0.245 | N5: 0.401 | O5: 0.297 | P5: 0.389 | Q5: 0.542 | R5: 0.395 | S5: 0.362 | T5: 137 | U5: 2.1 | V5: 21.3 | W5: 1.6 | X5: 3.7
A6: 2023 | B6: =_xlfn.XLOOKUP(C6,ID!$J$2:$J$3825,ID!$I$2:$I$3825,"n/a",0,1) -> 29695 | C6: Matt McLain | D6: CIN | E6: 89 | F6: 403 | G6: 16 | H6: 65 | I6: 50 | J6: 14 | K6: 0.077 | L6: 0.285 | M6: 0.216 | N6: 0.385 | O6: 0.29 | P6: 0.357 | Q6: 0.507 | R6: 0.37 | S6: 0.332 | T6: 129 | U6: 0.4 | V6: 14.7 | W6: 3.7 | X6: 3.2
A7: 2023 | B7: =_xlfn.XLOOKUP(C7,ID!$J$2:$J$3825,ID!$I$2:$I$3825,"n/a",0,1) -> 26121 | C7: Francisco Alvarez | D7: NYM | E7: 123 | F7: 423 | G7: 25 | H7: 51 | I7: 63 | J7: 2 | K7: 0.08 | L7: 0.26 | M7: 0.228 | N7: 0.222 | O7: 0.209 | P7: 0.284 | Q7: 0.437 | R7: 0.31 | S7: 0.306 | T7: 96 | U7: -2.8 | V7: -4.8 | W7: 20.1 | X7: 3
A8: 2023 | B8: =_xlfn.XLOOKUP(C8,ID!$J$2:$J$3825,ID!$I$2:$I$3825,"n/a",0,1) -> n/a | C8: Josh Jung | D8: TEX | E8: 122 | F8: 515 | G8: 23 | H8: 75 | I8: 70 | J8: 1 | K8: 0.058 | L8: 0.293 | M8: 0.201 | N8: 0.34 | O8: 0.266 | P8: 0.315 | Q8: 0.467 | R8: 0.334 | S8: 0.334 | T8: 114 | U8: -3.4 | V8: 5.2 | W8: 5.4 | X8: 2.8
A9: 2023 | B9: =_xlfn.XLOOKUP(C9,ID!$J$2:$J$3825,ID!$I$2:$I$3825,"n/a",0,1) -> 29766 | C9: Zack Gelof | D9: OAK | E9: 69 | F9: 300 | G9: 14 | H9: 40 | I9: 32 | J9: 14 | K9: 0.087 | L9: 0.273 | M9: 0.237 | N9: 0.331 | O9: 0.267 | P9: 0.337 | Q9: 0.504 | R9: 0.357 | S9: 0.33 | T9: 132 | U9: 2.2 | V9: 13.8 | W9: 3 | X9: 2.7
A10: 2023 | B10: =_xlfn.XLOOKUP(C10,ID!$J$2:$J$3825,ID!$I$2:$I$3825,"n/a",0,1) -> 27534 | C10: Edouard Julien | D10: MIN | E10: 109 | F10: 408 | G10: 16 | H10: 60 | I10: 37 | J10: 3 | K10: 0.157 | L10: 0.314 | M10: 0.195 | N10: 0.371 | O10: 0.263 | P10: 0.381 | Q10: 0.459 | R10: 0.366 | S10: 0.343 | T10: 134 | U10: -1.2 | V10: 15.4 | W10: -2.4 | X10: 2.7
A11: 2023 | B11: =_xlfn.XLOOKUP(C11,ID!$J$2:$J$3825,ID!$I$2:$I$3825,"n/a",0,1) -> 27478 | C11: Patrick Bailey | D11: SFG | E11: 97 | F11: 353 | G11: 7 | H11: 29 | I11: 48 | J11: 1 | K11: 0.059 | L11: 0.283 | M11: 0.126 | N11: 0.314 | O11: 0.233 | P11: 0.285 | Q11: 0.359 | R11: 0.282 | S11: 0.312 | T11: 77 | U11: -0.3 | V11: -10.6 | W11: 25.5 | X11: 2.7
A12: 2023 | B12: =_xlfn.XLOOKUP(C12,ID!$J$2:$J$3825,ID!$I$2:$I$3825,"n/a",0,1) -> 19354 | C12: Luke Raley | D12: TBR | E12: 118 | F12: 406 | G12: 19 | H12: 56 | I12: 49 | J12: 14 | K12: 0.069 | L12: 0.315 | M12: 0.241 | N12: 0.33 | O12: 0.249 | P12: 0.333 | Q12: 0.49 | R12: 0.353 | S12: 0.328 | T12: 129 | U12: 2 | V12: 16.2 | W12: -5.6 | X12: 2.4
A13: 2023 | B13: =_xlfn.XLOOKUP(C13,ID!$J$2:$J$3825,ID!$I$2:$I$3825,"n/a",0,1) -> 23003 | C13: Yainer Diaz | D13: HOU | E13: 104 | F13: 377 | G13: 23 | H13: 51 | I13: 60 | J13: 0 | K13: 0.029 | L13: 0.196 | M13: 0.256 | N13: 0.292 | O13: 0.282 | P13: 0.308 | Q13: 0.538 | R13: 0.354 | S13: 0.358 | T13: 127 | U13: -1.7 | V13: 10.3 | W13: 1.1 | X13: 2.4
... A626: 2021 | B626: =_xlfn.XLOOKUP(C626,ID!$J$2:$J$3825,ID!$I$2:$I$3825,"n/a",0,1) -> 19903 | C626: Adonis Medina | D626: PHI | E626: 4 | F626: 1 | G626: 0 | H626: 0 | I626: 0 | J626: 0 | K626: 0 | L626: 1 | M626: 0 | N626: 0 | O626: 0 | P626: 0 | Q626: 0 | R626: 0 | S626: 0 | T626: -100 | U626: 0 | V626: -0.3 | W626: 0.1 | X626: 0
A627: 2021 | B627: =_xlfn.XLOOKUP(C627,ID!$J$2:$J$3825,ID!$I$2:$I$3825,"n/a",0,1) -> n/a | C627: Ramón Rosso | D627: PHI | E627: 7 | F627: 1 | G627: 0 | H627: 0 | I627: 0 | J627: 0 | K627: 0 | L627: 0 | M627: 0 | N627: 0 | O627: 0 | P627: 0 | Q627: 0 | R627: 0 | T627: -100 | U627: 0 | V627: -0.3 | W627: 0.1 | X627: 0
A628: 2021 | B628: =_xlfn.XLOOKUP(C628,ID!$J$2:$J$3825,ID!$I$2:$I$3825,"n/a",0,1) -> n/a | C628: Hans Crouse | D628: PHI | E628: 2 | F628: 1 | G628: 0 | H628: 0 | I628: 0 | J628: 0 | K628: 0 | L628: 1 | M628: 0 | N628: 0 | O628: 0 | P628: 0 | Q628: 0 | R628: 0 | S628: 0 | T628: -100 | U628: 0 | V628: -0.3 | W628: 0.1 | X628: 0
A629: 2021 | B629: =_xlfn.XLOOKUP(C629,ID!$J$2:$J$3825,ID!$I$2:$I$3825,"n/a",0,1) -> 21524 | C629: Joey Bart | D629: SFG | E629: 2 | F629: 6 | G629: 0 | H629: 1 | I629: 1 | J629: 0 | K629: 0 | L629: 0.333 | M629: 0 | N629: 0.5 | O629: 0.333 | P629: 0.333 | Q629: 0.333 | R629: 0.293 | S629: 0.321 | T629: 85 | U629: 0 | V629: -0.1 | W629: -0.2 | X629: 0
A630: 2021 | B630: =_xlfn.XLOOKUP(C630,ID!$J$2:$J$3825,ID!$I$2:$I$3825,"n/a",0,1) -> 16291 | C630: Nick Ciuffo | D630: BAL | E630: 2 | F630: 6 | G630: 0 | H630: 0 | I630: 0 | J630: 0 | K630: 0.167 | L630: 0.167 | M630: 0.2 | N630: 0.25 | O630: 0.2 | P630: 0.333 | Q630: 0.4 | R630: 0.322 | S630: 0.275 | T630: 102 | U630: 0.1 | V630: 0.1 | W630: -0.4 | X630: 0
A631: 2021 | B631: =_xlfn.XLOOKUP(C631,ID!$J$2:$J$3825,ID!$I$2:$I$3825,"n/a",0,1) -> 19569 | C631: David Bednar | D631: PIT | E631: 61 | F631: 1 | G631: 0 | H631: 0 | I631: 0 | J631: 0 | K631: 0 | L631: 1 | M631: 0 | N631: 0 | O631: 0 | P631: 0 | Q631: 0 | R631: 0 | S631: 0 | T631: -100 | U631: 0 | V631: -0.3 | W631: 0.1 | X631: 0
A632: 2021 | B632: =_xlfn.XLOOKUP(C632,ID!$J$2:$J$3825,ID!$I$2:$I$3825,"n/a",0,1) -> n/a | C632: Sean Poppen | D632: 3 Tms | E632: 24 | F632: 1 | G632: 0 | H632: 0 | I632: 0 | J632: 0 | K632: 0 | L632: 1 | M632: 0 | N632: 0 | O632: 0 | P632: 0 | Q632: 0 | R632: 0 | S632: 0 | T632: -100 | U632: 0 | V632: -0.3 | W632: 0.1 | X632: 0
A633: 2021 | B633: =_xlfn.XLOOKUP(C633,ID!$J$2:$J$3825,ID!$I$2:$I$3825,"n/a",0,1) -> 25376 | C633: Nick Mears | D633: PIT | E633: 30 | F633: 1 | G633: 0 | H633: 0 | I633: 0 | J633: 0 | K633: 0 | L633: 1 | M633: 0 | N633: 0 | O633: 0 | P633: 0 | Q633: 0 | R633: 0 | S633: 0 | T633: -100 | U633: 0 | V633: -0.3 | W633: 0.1 | X633: 0
A634: 2021 | B634: =_xlfn.XLOOKUP(C634,ID!$J$2:$J$3825,ID!$I$2:$I$3825,"n/a",0,1) -> 19879 | C634: Tanner Houck | D634: BOS | E634: 18 | F634: 1 | G634: 0 | H634: 0 | I634: 0 | J634: 0 | K634: 0 | L634: 1 | M634: 0 | N634: 0 | O634: 0 | P634: 0 | Q634: 0 | R634: 0 | S634: 0 | T634: -100 | U634: 0 | V634: -0.3 | W634: 0.1 | X634: 0
A635: 2021 | B635: =_xlfn.XLOOKUP(C635,ID!$J$2:$J$3825,ID!$I$2:$I$3825,"n/a",0,1) -> n/a | C635: R.J. Alaniz | D635: CIN | E635: 3 | F635: 1 | G635: 0 | H635: 0 | I635: 0 | J635: 0 | K635: 0 | L635: 1 | M635: 0 | N635: 0 | O635: 0 | P635: 0 | Q635: 0 | R635: 0 | S635: 0 | T635: -100 | U635: 0 | V635: -0.3 | W635: 0.1 | X635: 0
A636: 2021 | B636: =_xlfn.XLOOKUP(C636,ID!$J$2:$J$3825,ID!$I$2:$I$3825,"n/a",0,1) -> n/a | C636: Ryan Hendrix | D636: CIN | E636: 36 | F636: 1 | G636: 0 | H636: 0 | I636: 0 | J636: 0 | K636: 0 | L636: 0 | M636: 0 | N636: 0 | O636: 0 | P636: 0 | Q636: 0 | R636: 0 | S636: 0.229 | T636: -100 | U636: 0 | V636: -0.3 | W636: 0.1 | X636: 0
A637: 2021 | B637: =_xlfn.XLOOKUP(C637,ID!$J$2:$J$3825,ID!$I$2:$I$3825,"n/a",0,1) -> 16377 | C637: Ryan Castellani | D637: COL | E637: 1 | F637: 1 | G637: 0 | H637: 0 | I637: 0 | J637: 0 | K637: 0 | L637: 0 | M637: 0 | N637: 0 | O637: 0 | P637: 0 | Q637: 0 | R637: 0 | S637: 0.128 | T637: -100 | U637: 0 | V637: -0.3 | W637: 0.1 | X637: 0
A638: 2021 | B638: =_xlfn.XLOOKUP(C638,ID!$J$2:$J$3825,ID!$I$2:$I$3825,"n/a",0,1) -> 21446 | C638: Ryan Feltner | D638: COL | E638: 2 | F638: 1 | G638: 0 | H638: 0 | I638: 0 | J638: 0 | K638: 0 | L638: 1 | M638: 0 | N638: 0 | O638: 0 | P638: 0 | Q638: 0 | R638: 0 | S638: 0 | T638: -100 | U638: 0 | V638: -0.3 | W638: 0.1 | X638: 0
A639: 2021 | B639: =_xlfn.XLOOKUP(C639,ID!$J$2:$J$3825,ID!$I$2:$I$3825,"n/a",0,1) -> 20302 | C639: David Peterson | D639: NYM | E639: 16 | F639: 20 | G639: 0 | H639: 2 | I639: 0 | J639: 0 | K639: 0 | L639: 0.5 | M639: 0.063 | N639: 0.167 | O639: 0.063 | P639: 0.118 | Q639: 0.125 | R639: 0.116 | S639: 0.114 | T639: -30 | U639: 0.1 | V639: -3.2 | W639: 2.4 | X639: 0
... A1078: 2019 | B1078: =_xlfn.XLOOKUP(C1078,ID!$J$2:$J$3825,ID!$I$2:$I$3825,"n/a",0,1) -> 17982 | C1078: Ty France | D1078: SDP | E1078: 69 | F1078: 201 | G1078: 7 | H1078: 20 | I1078: 24 | J1078: 0 | K1078: 0.045 | L1078: 0.244 | M1078: 0.168 | N1078: 0.279 | O1078: 0.234 | P1078: 0.294 | Q1078: 0.402 | R1078: 0.296 | S1078: 0.294 | T1078: 84 | U1078: -1.4 | V1078: -5.7 | W1078: -0.8 | X1078: 0
A1079: 2019 | B1079: =_xlfn.XLOOKUP(C1079,ID!$J$2:$J$3825,ID!$I$2:$I$3825,"n/a",0,1) -> n/a | C1079: Matt Carasiti | D1079: SEA | E1079: 11 | F1079: 1 | G1079: 0 | H1079: 0 | I1079: 0 | J1079: 0 | K1079: 0 | L1079: 0 | M1079: 0 | N1079: 0 | O1079: 0 | P1079: 0 | Q1079: 0 | R1079: 0 | T1079: -100 | U1079: 0 | V1079: -0.3 | W1079: 0.1 | X1079: 0
A1080: 2019 | B1080: =_xlfn.XLOOKUP(C1080,ID!$J$2:$J$3825,ID!$I$2:$I$3825,"n/a",0,1) -> 13801 | C1080: Austin Adams | D1080: 2 Tms | E1080: 30 | F1080: 1 | G1080: 0 | H1080: 0 | I1080: 0 | J1080: 0 | K1080: 0 | L1080: 1 | M1080: 0 | N1080: 0 | O1080: 0 | P1080: 0 | Q1080: 0 | R1080: 0 | S1080: 0 | T1080: -100 | U1080: 0 | V1080: -0.3 | W1080: 0.1 | X1080: 0
A1081: 2019 | B1081: =_xlfn.XLOOKUP(C1081,ID!$J$2:$J$3825,ID!$I$2:$I$3825,"n/a",0,1) -> 19268 | C1081: Justin Dunn | D1081: SEA | E1081: 4 | F1081: 1 | G1081: 0 | H1081: 0 | I1081: 0 | J1081: 0 | K1081: 0 | L1081: 1 | M1081: 0 | N1081: 0 | O1081: 0 | P1081: 0 | Q1081: 0 | R1081: 0 | S1081: 0 | T1081: -100 | U1081: 0 | V1081: -0.3 | W1081: 0.1 | X1081: 0
A1082: 2019 | B1082: =_xlfn.XLOOKUP(C1082,ID!$J$2:$J$3825,ID!$I$2:$I$3825,"n/a",0,1) -> n/a | C1082: Tanner Anderson | D1082: OAK | E1082: 6 | F1082: 1 | G1082: 0 | H1082: 0 | I1082: 0 | J1082: 0 | K1082: 0 | L1082: 1 | M1082: 0 | N1082: 0 | O1082: 0 | P1082: 0 | Q1082: 0 | R1082: 0 | S1082: 0 | T1082: -100 | U1082: 0 | V1082: -0.3 | W1082: 0.1 | X1082: 0
A1083: 2019 | B1083: =_xlfn.XLOOKUP(C1083,ID!$J$2:$J$3825,ID!$I$2:$I$3825,"n/a",0,1) -> 17034 | C1083: Sean Reid-Foley | D1083: TOR | E1083: 9 | F1083: 1 | G1083: 0 | H1083: 0 | I1083: 0 | J1083: 0 | K1083: 0 | L1083: 1 | M1083: 0 | N1083: 0 | O1083: 0 | P1083: 0 | Q1083: 0 | R1083: 0 | S1083: 0 | T1083: -100 | U1083: 0 | V1083: -0.3 | W1083: 0.1 | X1083: 0
A1084: 2019 | B1084: =_xlfn.XLOOKUP(C1084,ID!$J$2:$J$3825,ID!$I$2:$I$3825,"n/a",0,1) -> 19269 | C1084: T.J. Zeuch | D1084: TOR | E1084: 5 | F1084: 1 | G1084: 0 | H1084: 0 | I1084: 0 | J1084: 0 | K1084: 0 | L1084: 1 | M1084: 0 | N1084: 0 | O1084: 0 | P1084: 0 | Q1084: 0 | R1084: 0 | S1084: 0 | T1084: -100 | U1084: 0 | V1084: -0.3 | W1084: 0.1 | X1084: 0
A1085: 2019 | B1085: =_xlfn.XLOOKUP(C1085,ID!$J$2:$J$3825,ID!$I$2:$I$3825,"n/a",0,1) -> 20632 | C1085: Elvis Luciano | D1085: TOR | E1085: 25 | F1085: 1 | G1085: 0 | H1085: 0 | I1085: 0 | J1085: 0 | K1085: 0 | L1085: 1 | M1085: 0 | N1085: 0 | O1085: 0 | P1085: 0 | Q1085: 0 | R1085: 0 | S1085: 0 | T1085: -100 | U1085: 0 | V1085: -0.3 | W1085: 0.1 | X1085: 0
A1086: 2019 | B1086: =_xlfn.XLOOKUP(C1086,ID!$J$2:$J$3825,ID!$I$2:$I$3825,"n/a",0,1) -> 15690 | C1086: Jimmy Cordero | D1086: 2 Tms | E1086: 31 | F1086: 1 | G1086: 0 | H1086: 0 | I1086: 0 | J1086: 0 | K1086: 0 | L1086: 0 | M1086: 0 | N1086: 0 | O1086: 0 | P1086: 0 | Q1086: 0 | R1086: 0 | T1086: -100 | U1086: 0 | V1086: -0.3 | W1086: 0.1 | X1086: 0
A1087: 2019 | B1087: =_xlfn.XLOOKUP(C1087,ID!$J$2:$J$3825,ID!$I$2:$I$3825,"n/a",0,1) -> 19979 | C1087: Zach Plesac | D1087: CLE | E1087: 21 | F1087: 1 | G1087: 0 | H1087: 0 | I1087: 0 | J1087: 0 | K1087: 0 | L1087: 0 | M1087: 0 | N1087: 0 | O1087: 0 | P1087: 0 | Q1087: 0 | R1087: 0 | T1087: -100 | U1087: 0 | V1087: -0.3 | W1087: 0.1 | X1087: 0
A1088: 2019 | B1088: =_xlfn.XLOOKUP(C1088,ID!$J$2:$J$3825,ID!$I$2:$I$3825,"n/a",0,1) -> 12575 | C1088: Nick Ramirez | D1088: DET | E1088: 46 | F1088: 1 | G1088: 0 | H1088: 0 | I1088: 0 | J1088: 0 | K1088: 0 | L1088: 1 | M1088: 0 | N1088: 0 | O1088: 0 | P1088: 0 | Q1088: 0 | R1088: 0 | S1088: 0 | T1088: -100 | U1088: 0 | V1088: -0.3 | W1088: 0.1 | X1088: 0
A1089: 2019 | B1089: =_xlfn.XLOOKUP(C1089,ID!$J$2:$J$3825,ID!$I$2:$I$3825,"n/a",0,1) -> 16631 | C1089: Jeff Brigham | D1089: MIA | E1089: 32 | F1089: 1 | G1089: 0 | H1089: 0 | I1089: 0 | J1089: 0 | K1089: 0 | L1089: 1 | M1089: 0 | N1089: 0 | O1089: 0 | P1089: 0 | Q1089: 0 | R1089: 0 | S1089: 0 | T1089: -100 | U1089: 0 | V1089: -0.3 | W1089: 0.1 | X1089: 0
A1090: 2019 | B1090: =_xlfn.XLOOKUP(C1090,ID!$J$2:$J$3825,ID!$I$2:$I$3825,"n/a",0,1) -> 18297 | C1090: Tyler Kinley | D1090: MIA | E1090: 52 | F1090: 1 | G1090: 0 | H1090: 0 | I1090: 0 | J1090: 0 | K1090: 0 | L1090: 1 | M1090: 0 | N1090: 0 | O1090: 0 | P1090: 0 | Q1090: 0 | R1090: 0 | S1090: 0 | T1090: -100 | U1090: 0 | V1090: -0.3 | W1090: 0.1 | X1090: 0
A1091: 2019 | B1091: =_xlfn.XLOOKUP(C1091,ID!$J$2:$J$3825,ID!$I$2:$I$3825,"n/a",0,1) -> n/a | C1091: José Quijada | D1091: MIA | E1091: 34 | F1091: 1 | G1091: 0 | H1091: 0 | I1091: 0 | J1091: 0 | K1091: 0 | L1091: 1 | M1091: 0 | N1091: 0 | O1091: 0 | P1091: 0 | Q1091: 0 | R1091: 0 | S1091: 0 | T1091: -100 | U1091: 0 | V1091: -0.3 | W1091: 0.1 | X1091: 0
A1092: 2019 | B1092: =_xlfn.XLOOKUP(C1092,ID!$J$2:$J$3825,ID!$I$2:$I$3825,"n/a",0,1) -> n/a | C1092: Gerardo Reyes | D1092: SDP | E1092: 27 | F1092: 1 | G1092: 0 | H1092: 0 | I1092: 0 | J1092: 0 | K1092: 0 | L1092: 1 | M1092: 0 | N1092: 0 | O1092: 0 | P1092: 0 | Q1092: 0 | R1092: 0 | S1092: 0 | T1092: -100 | U1092: 0 | V1092: -0.3 | W1092: 0.1 | X1092: 0
A1093: 2019 | B1093: =_xlfn.XLOOKUP(C1093,ID!$J$2:$J$3825,ID!$I$2:$I$3825,"n/a",0,1) -> 20039 | C1093: Adrian Morejon | D1093: SDP | E1093: 5 | F1093: 1 | G1093: 0 | H1093: 0 | I1093: 0 | J1093: 0 | K1093: 0 | L1093: 1 | M1093: 0 | N1093: 0 | O1093: 0 | P1093: 0 | Q1093: 0 | R1093: 0 | S1093: 0 | T1093: -100 | U1093: 0 | V1093: -0.3 | W1093: 0.1 | X1093: 0
A1094: 2019 | B1094: =_xlfn.XLOOKUP(C1094,ID!$J$2:$J$3825,ID!$I$2:$I$3825,"n/a",0,1) -> 14665 | C1094: Jandel Gustave | D1094: SFG | E1094: 23 | F1094: 1 | G1094: 0 | H1094: 0 | I1094: 0 | J1094: 0 | K1094: 0 | L1094: 1 | M1094: 0 | N1094: 0 | O1094: 0 | P1094: 0 | Q1094: 0 | R1094: 0 | S1094: 0 | T1094: -100 | U1094: 0 | V1094: -0.3 | W1094: 0.1 | X1094: 0
A1095: 2019 | B1095: =_xlfn.XLOOKUP(C1095,ID!$J$2:$J$3825,ID!$I$2:$I$3825,"n/a",0,1) -> 8004 | C1095: Marcus Walden | D1095: BOS | E1095: 70 | F1095: 1 | G1095: 0 | H1095: 0 | I1095: 0 | J1095: 0 | K1095: 0 | L1095: 1 | M1095: 0 | N1095: 0 | O1095: 0 | P1095: 0 | Q1095: 0 | R1095: 0 | S1095: 0 | T1095: -100 | U1095: 0 | V1095: -0.3 | W1095: 0.1 | X1095: 0
A1096: 2019 | B1096: =_xlfn.XLOOKUP(C1096,ID!$J$2:$J$3825,ID!$I$2:$I$3825,"n/a",0,1) -> n/a | C1096: Rookie Davis | D1096: PIT | E1096: 5 | F1096: 1 | G1096: 0 | H1096: 0 | I1096: 0 | J1096: 0 | K1096: 0 | L1096: 0 | M1096: 0 | N1096: 0 | O1096: 0 | P1096: 0 | Q1096: 0 | R1096: 0 | S1096: 0.106 | T1096: -100 | U1096: 0 | V1096: -0.3 | W1096: 0.1 | X1096: 0
A1097: 2019 | B1097: =_xlfn.XLOOKUP(C1097,ID!$J$2:$J$3825,ID!$I$2:$I$3825,"n/a",0,1) -> n/a | C1097: Randy Rosario | D1097: 2 Tms | E1097: 19 | F1097: 1 | G1097: 0 | H1097: 0 | I1097: 0 | J1097: 0 | K1097: 0 | L1097: 0 | M1097: 0 | N1097: 0 | O1097: 0 | P1097: 0 | Q1097: 0 | R1097: 0 | S1097: 0.081 | T1097: -100 | U1097: 0 | V1097: -0.3 | W1097: 0.1 | X1097: 0
A1098: 2019 | B1098: =_xlfn.XLOOKUP(C1098,ID!$J$2:$J$3825,ID!$I$2:$I$3825,"n/a",0,1) -> 14677 | C1098: Duane Underwood Jr. | D1098: CHC | E1098: 12 | F1098: 1 | G1098: 0 | H1098: 0 | I1098: 0 | J1098: 0 | K1098: 0 | L1098: 1 | M1098: 0 | N1098: 0 | O1098: 0 | P1098: 0 | Q1098: 0 | R1098: 0 | S1098: 0 | T1098: -100 | U1098: 0 | V1098: -0.3 | W1098: 0.1 | X1098: 0
A1099: 2019 | B1099: =_xlfn.XLOOKUP(C1099,ID!$J$2:$J$3825,ID!$I$2:$I$3825,"n/a",0,1) -> n/a | C1099: James Norwood | D1099: CHC | E1099: 9 | F1099: 1 | G1099: 0 | H1099: 0 | I1099: 0 | J1099: 0 | K1099: 0 | L1099: 0 | M1099: 0 | N1099: 0 | O1099: 0 | P1099: 0 | Q1099: 0 | R1099: 0 | S1099: 0.335 | T1099: -100 | U1099: 0 | V1099: -0.3 | W1099: 0.1 | X1099: 0
... A1108: 2019 | B1108: =_xlfn.XLOOKUP(C1108,ID!$J$2:$J$3825,ID!$I$2:$I$3825,"n/a",0,1) -> n/a | C1108: Pedro Payano | D1108: TEX | E1108: 6 | F1108: 1 | G1108: 0 | H1108: 0 | I1108: 0 | J1108: 0 | K1108: 0 | L1108: 1 | M1108: 0 | N1108: 0 | O1108: 0 | P1108: 0 | Q1108: 0 | R1108: 0 | S1108: 0 | T1108: -100 | U1108: 0 | V1108: -0.3 | W1108: 0.1 | X1108: 0
A1109: 2019 | B1109: =_xlfn.XLOOKUP(C1109,ID!$J$2:$J$3825,ID!$I$2:$I$3825,"n/a",0,1) -> n/a | C1109: Keury Mella | D1109: CIN | E1109: 2 | F1109: 1 | G1109: 0 | H1109: 0 | I1109: 0 | J1109: 0 | K1109: 0 | L1109: 1 | M1109: 0 | N1109: 0 | O1109: 0 | P1109: 0 | Q1109: 0 | R1109: 0 | T1109: -100 | U1109: 0 | V1109: -0.3 | W1109: 0.1 | X1109: 0
A1110: 2019 | B1110: =_xlfn.XLOOKUP(C1110,ID!$J$2:$J$3825,ID!$I$2:$I$3825,"n/a",0,1) -> 19995 | C1110: Joel Kuhnel | D1110: CIN | E1110: 11 | F1110: 1 | G1110: 0 | H1110: 0 | I1110: 0 | J1110: 0 | K1110: 0 | L1110: 0 | M1110: 0 | N1110: 0 | O1110: 0 | P1110: 0 | Q1110: 0 | R1110: 0 | S1110: 0.042 | T1110: -100 | U1110: 0 | V1110: -0.3 | W1110: 0.1 | X1110: 0
A1111: 2019 | B1111: =_xlfn.XLOOKUP(C1111,ID!$J$2:$J$3825,ID!$I$2:$I$3825,"n/a",0,1) -> n/a | C1111: Sam Howard | D1111: COL | E1111: 20 | F1111: 1 | G1111: 0 | H1111: 0 | I1111: 0 | J1111: 0 | K1111: 0 | L1111: 1 | M1111: 0 | N1111: 0 | O1111: 0 | P1111: 0 | Q1111: 0 | R1111: 0 | S1111: 0 | T1111: -100 | U1111: 0 | V1111: -0.3 | W1111: 0.1 | X1111: 0
A1112: 2019 | B1112: =_xlfn.XLOOKUP(C1112,ID!$J$2:$J$3825,ID!$I$2:$I$3825,"n/a",0,1) -> n/a | C1112: Rico Garcia | D1112: COL | E1112: 2 | F1112: 1 | G1112: 0 | H1112: 0 | I1112: 0 | J1112: 0 | K1112: 0 | L1112: 1 | M1112: 0 | N1112: 0 | O1112: 0 | P1112: 0 | Q1112: 0 | R1112: 0 | S1112: 0 | T1112: -100 | U1112: 0 | V1112: -0.3 | W1112: 0.1 | X1112: 0
A1113: 2019 | B1113: =_xlfn.XLOOKUP(C1113,ID!$J$2:$J$3825,ID!$I$2:$I$3825,"n/a",0,1) -> 14773 | C1113: Yu Chang | D1113: CLE | E1113: 28 | F1113: 84 | G1113: 1 | H1113: 8 | I1113: 6 | J1113: 0 | K1113: 0.131 | L1113: 0.262 | M1113: 0.096 | N1113: 0.24 | O1113: 0.178 | P1113: 0.286 | Q1113: 0.274 | R1113: 0.254 | S1113: 0.299 | T1113: 53 | U1113: -0.1 | V1113: -5.1 | W1113: 1.9 | X1113: 0
A1114: 2019 | B1114: =_xlfn.XLOOKUP(C1114,ID!$J$2:$J$3825,ID!$I$2:$I$3825,"n/a",0,1) -> 16725 | C1114: Jose Trevino | D1114: TEX | E1114: 40 | F1114: 126 | G1114: 2 | H1114: 18 | I1114: 13 | J1114: 0 | K1114: 0.024 | L1114: 0.214 | M1114: 0.125 | N1114: 0.312 | O1114: 0.258 | P1114: 0.272 | Q1114: 0.383 | R1114: 0.274 | S1114: 0.258 | T1114: 59 | U1114: -2 | V1114: -8.7 | W1114: 3.9 | X1114: 0
A1115: 2019 | B1115: =_xlfn.XLOOKUP(C1115,ID!$J$2:$J$3825,ID!$I$2:$I$3825,"n/a",0,1) -> 16587 | C1115: Erik Swanson | D1115: SEA | E1115: 27 | F1115: 2 | G1115: 0 | H1115: 0 | I1115: 0 | J1115: 0 | K1115: 0 | L1115: 0.5 | M1115: 0 | N1115: 0 | O1115: 0 | P1115: 0 | Q1115: 0 | R1115: 0 | S1115: 0 | T1115: -100 | U1115: 0 | V1115: -0.5 | W1115: 0.2 | X1115: 0
A1116: 2019 | B1116: =_xlfn.XLOOKUP(C1116,ID!$J$2:$J$3825,ID!$I$2:$I$3825,"n/a",0,1) -> 17285 | C1116: Justus Sheffield | D1116: SEA | E1116: 8 | F1116: 2 | G1116: 0 | H1116: 0 | I1116: 0 | J1116: 0 | K1116: 0 | L1116: 1 | M1116: 0 | N1116: 0 | O1116: 0 | P1116: 0 | Q1116: 0 | R1116: 0 | S1116: 0 | T1116: -100 | U1116: 0 | V1116: -0.5 | W1116: 0.2 | X1116: 0
A1117: 2019 | B1117: =_xlfn.XLOOKUP(C1117,ID!$J$2:$J$3825,ID!$I$2:$I$3825,"n/a",0,1) -> 20633 | C1117: Yusei Kikuchi | D1117: SEA | E1117: 32 | F1117: 2 | G1117: 0 | H1117: 0 | I1117: 0 | J1117: 0 | K1117: 0 | L1117: 0.5 | M1117: 0 | N1117: 0 | O1117: 0 | P1117: 0 | Q1117: 0 | R1117: 0 | S1117: 0 | T1117: -100 | U1117: 0 | V1117: -0.5 | W1117: 0.2 | X1117: 0
A1118: 2019 | B1118: =_xlfn.XLOOKUP(C1118,ID!$J$2:$J$3825,ID!$I$2:$I$3825,"n/a",0,1) -> 19479 | C1118: Aaron Civale | D1118: CLE | E1118: 10 | F1118: 2 | G1118: 0 | H1118: 0 | I1118: 0 | J1118: 0 | K1118: 0 | L1118: 0.5 | M1118: 0 | N1118: 0 | O1118: 0 | P1118: 0 | Q1118: 0 | R1118: 0 | S1118: 0.131 | T1118: -100 | U1118: 0 | V1118: -0.6 | W1118: 0.2 | X1118: 0
A1119: 2019 | B1119: =_xlfn.XLOOKUP(C1119,ID!$J$2:$J$3825,ID!$I$2:$I$3825,"n/a",0,1) -> 12699 | C1119: Ryan Carpenter | D1119: DET | E1119: 9 | F1119: 2 | G1119: 0 | H1119: 0 | I1119: 0 | J1119: 0 | K1119: 0 | L1119: 0.5 | M1119: 0 | N1119: 0 | O1119: 0 | P1119: 0 | Q1119: 0 | R1119: 0 | S1119: 0.009 | T1119: -100 | U1119: 0 | V1119: -0.6 | W1119: 0.2 | X1119: 0
A1120: 2019 | B1120: =_xlfn.XLOOKUP(C1120,ID!$J$2:$J$3825,ID!$I$2:$I$3825,"n/a",0,1) -> 19447 | C1120: Patrick Sandoval | D1120: LAA | E1120: 10 | F1120: 2 | G1120: 0 | H1120: 0 | I1120: 0 | J1120: 0 | K1120: 0 | L1120: 1 | M1120: 0 | N1120: 0 | O1120: 0 | P1120: 0 | Q1120: 0 | R1120: 0 | S1120: 0 | T1120: -100 | U1120: 0 | V1120: -0.6 | W1120: 0.2 | X1120: 0
A1121: 2019 | B1121: =_xlfn.XLOOKUP(C1121,ID!$J$2:$J$3825,ID!$I$2:$I$3825,"n/a",0,1) -> 19867 | C1121: Griffin Canning | D1121: LAA | E1121: 18 | F1121: 2 | G1121: 0 | H1121: 0 | I1121: 0 | J1121: 0 | K1121: 0 | L1121: 0.5 | M1121: 0 | N1121: 0 | O1121: 0 | P1121: 0 | Q1121: 0 | R1121: 0 | S1121: 0.033 | T1121: -100 | U1121: 0 | V1121: -0.6 | W1121: 0.2 | X1121: 0
... A1424: 2018 | B1424: =_xlfn.XLOOKUP(C1424,ID!$J$2:$J$3825,ID!$I$2:$I$3825,"n/a",0,1) -> n/a | C1424: Yacksel Ríos | D1424: PHI | E1424: 36 | F1424: 1 | G1424: 0 | H1424: 0 | I1424: 0 | J1424: 0 | K1424: 0 | L1424: 1 | M1424: 0 | N1424: 0 | O1424: 0 | P1424: 0 | Q1424: 0 | R1424: 0 | S1424: 0 | T1424: -100 | U1424: 0 | V1424: -0.3 | W1424: 0.1 | X1424: 0
A1425: 2018 | B1425: =_xlfn.XLOOKUP(C1425,ID!$J$2:$J$3825,ID!$I$2:$I$3825,"n/a",0,1) -> 19361 | C1425: Corbin Burnes | D1425: MIL | E1425: 30 | F1425: 1 | G1425: 0 | H1425: 0 | I1425: 0 | J1425: 0 | K1425: 0 | L1425: 0 | M1425: 0 | N1425: 0 | O1425: 0 | P1425: 0 | Q1425: 0 | R1425: 0 | T1425: -100 | U1425: 0 | V1425: -0.3 | W1425: 0.1 | X1425: 0
A1426: 2018 | B1426: =_xlfn.XLOOKUP(C1426,ID!$J$2:$J$3825,ID!$I$2:$I$3825,"n/a",0,1) -> 15570 | C1426: Troy Scribner | D1426: ARI | E1426: 1 | F1426: 1 | G1426: 0 | H1426: 0 | I1426: 0 | J1426: 0 | K1426: 0 | L1426: 1 | M1426: 0 | N1426: 0 | O1426: 0 | P1426: 0 | Q1426: 0 | R1426: 0 | S1426: 0 | T1426: -100 | U1426: 0 | V1426: -0.3 | W1426: 0.1 | X1426: 0
A1427: 2018 | B1427: =_xlfn.XLOOKUP(C1427,ID!$J$2:$J$3825,ID!$I$2:$I$3825,"n/a",0,1) -> 19756 | C1427: Yoshihisa Hirano | D1427: ARI | E1427: 75 | F1427: 1 | G1427: 0 | H1427: 0 | I1427: 0 | J1427: 0 | K1427: 0 | L1427: 0 | M1427: 0 | N1427: 0 | O1427: 0 | P1427: 0 | Q1427: 0 | R1427: 0 | S1427: 0.048 | T1427: -100 | U1427: 0 | V1427: -0.3 | W1427: 0.1 | X1427: 0
A1428: 2018 | B1428: =_xlfn.XLOOKUP(C1428,ID!$J$2:$J$3825,ID!$I$2:$I$3825,"n/a",0,1) -> 12237 | C1428: Dan Winkler | D1428: ATL | E1428: 69 | F1428: 1 | G1428: 0 | H1428: 0 | I1428: 0 | J1428: 0 | K1428: 0 | L1428: 0 | M1428: 0 | N1428: 0 | O1428: 0 | P1428: 0 | Q1428: 0 | R1428: 0 | S1428: 0.079 | T1428: -100 | U1428: 0 | V1428: -0.3 | W1428: 0.1 | X1428: 0
A1429: 2018 | B1429: =_xlfn.XLOOKUP(C1429,ID!$J$2:$J$3825,ID!$I$2:$I$3825,"n/a",0,1) -> 14764 | C1429: Wes Parsons | D1429: ATL | E1429: 1 | F1429: 1 | G1429: 0 | H1429: 0 | I1429: 0 | J1429: 0 | K1429: 0 | L1429: 1 | M1429: 0 | N1429: 0 | O1429: 0 | P1429: 0 | Q1429: 0 | R1429: 0 | S1429: 0 | T1429: -100 | U1429: 0 | V1429: -0.3 | W1429: 0.1 | X1429: 0
A1430: 2018 | B1430: =_xlfn.XLOOKUP(C1430,ID!$J$2:$J$3825,ID!$I$2:$I$3825,"n/a",0,1) -> 11012 | C1430: Kevin Shackelford | D1430: CIN | E1430: 5 | F1430: 1 | G1430: 0 | H1430: 0 | I1430: 0 | J1430: 0 | K1430: 0 | L1430: 1 | M1430: 0 | N1430: 0 | O1430: 0 | P1430: 0 | Q1430: 0 | R1430: 0 | S1430: 0 | T1430: -100 | U1430: 0 | V1430: -0.3 | W1430: 0.1 | X1430: 0
A1431: 2018 | B1431: =_xlfn.XLOOKUP(C1431,ID!$J$2:$J$3825,ID!$I$2:$I$3825,"n/a",0,1) -> 17237 | C1431: Austin Brice | D1431: CIN | E1431: 33 | F1431: 1 | G1431: 0 | H1431: 0 | I1431: 0 | J1431: 0 | K1431: 0 | L1431: 1 | M1431: 0 | N1431: 0 | O1431: 0 | P1431: 0 | Q1431: 0 | R1431: 0 | S1431: 0 | T1431: -100 | U1431: 0 | V1431: -0.3 | W1431: 0.1 | X1431: 0
A1432: 2018 | B1432: =_xlfn.XLOOKUP(C1432,ID!$J$2:$J$3825,ID!$I$2:$I$3825,"n/a",0,1) -> 17030 | C1432: Ariel Jurado | D1432: TEX | E1432: 12 | F1432: 1 | G1432: 0 | H1432: 0 | I1432: 0 | J1432: 0 | K1432: 0 | L1432: 0 | M1432: 0 | N1432: 0 | O1432: 0 | P1432: 0 | Q1432: 0 | R1432: 0 | T1432: -100 | U1432: 0 | V1432: -0.3 | W1432: 0.1 | X1432: 0
A1433: 2018 | B1433: =_xlfn.XLOOKUP(C1433,ID!$J$2:$J$3825,ID!$I$2:$I$3825,"n/a",0,1) -> 13420 | C1433: Matt Koch | D1433: ARI | E1433: 19 | F1433: 23 | G1433: 0 | H1433: 1 | I1433: 0 | J1433: 0 | K1433: 0.13 | L1433: 0.478 | M1433: 0 | N1433: 0.167 | O1433: 0.059 | P1433: 0.2 | Q1433: 0.059 | R1433: 0.147 | S1433: 0.162 | T1433: -17 | U1433: -0.3 | V1433: -3.6 | W1433: 2.8 | X1433: 0
A1434: 2018 | B1434: =_xlfn.XLOOKUP(C1434,ID!$J$2:$J$3825,ID!$I$2:$I$3825,"n/a",0,1) -> 15068 | C1434: Yency Almonte | D1434: COL | E1434: 14 | F1434: 1 | G1434: 0 | H1434: 0 | I1434: 0 | J1434: 0 | K1434: 0 | L1434: 0 | M1434: 0 | N1434: 0 | O1434: 0 | P1434: 0 | Q1434: 0 | R1434: 0 | S1434: 0.114 | T1434: -100 | U1434: 0 | V1434: -0.3 | W1434: 0.1 | X1434: 0
A1435: 2018 | B1435: =_xlfn.XLOOKUP(C1435,ID!$J$2:$J$3825,ID!$I$2:$I$3825,"n/a",0,1) -> 13012 | C1435: John Andreoli | D1435: 2 Tms | E1435: 26 | F1435: 67 | G1435: 0 | H1435: 4 | I1435: 4 | J1435: 2 | K1435: 0.075 | L1435: 0.284 | M1435: 0.033 | N1435: 0.326 | O1435: 0.23 | P1435: 0.284 | Q1435: 0.262 | R1435: 0.246 | S1435: 0.219 | T1435: 51 | U1435: 0.5 | V1435: -3.4 | W1435: 0.9 | X1435: 0
A1436: 2018 | B1436: =_xlfn.XLOOKUP(C1436,ID!$J$2:$J$3825,ID!$I$2:$I$3825,"n/a",0,1) -> 13284 | C1436: Darnell Sweeney | D1436: TOR | E1436: 2 | F1436: 4 | G1436: 0 | H1436: 0 | I1436: 0 | J1436: 0 | K1436: 0.5 | L1436: 0 | M1436: 0 | N1436: 0 | O1436: 0 | P1436: 0.5 | Q1436: 0 | R1436: 0.345 | S1436: 0.412 | T1436: 118 | U1436: -0.1 | V1436: 0 | W1436: -0.3 | X1436: 0
A1437: 2018 | B1437: =_xlfn.XLOOKUP(C1437,ID!$J$2:$J$3825,ID!$I$2:$I$3825,"n/a",0,1) -> 17062 | C1437: Grayson Greiner | D1437: DET | E1437: 30 | F1437: 116 | G1437: 0 | H1437: 9 | I1437: 12 | J1437: 0 | K1437: 0.147 | L1437: 0.276 | M1437: 0.063 | N1437: 0.313 | O1437: 0.219 | P1437: 0.328 | Q1437: 0.281 | R1437: 0.279 | S1437: 0.329 | T1437: 72 | U1437: -0.9 | V1437: -4.8 | W1437: 0.7 | X1437: 0
A1438: 2018 | B1438: =_xlfn.XLOOKUP(C1438,ID!$J$2:$J$3825,ID!$I$2:$I$3825,"n/a",0,1) -> 14875 | C1438: Caleb Smith | D1438: MIA | E1438: 16 | F1438: 26 | G1438: 0 | H1438: 0 | I1438: 1 | J1438: 0 | K1438: 0 | L1438: 0.5 | M1438: 0 | N1438: 0.333 | O1438: 0.136 | P1438: 0.136 | Q1438: 0.136 | R1438: 0.12 | S1438: 0.122 | T1438: -29 | U1438: 0 | V1438: -4.1 | W1438: 3.1 | X1438: 0
A1439: 2018 | B1439: =_xlfn.XLOOKUP(C1439,ID!$J$2:$J$3825,ID!$I$2:$I$3825,"n/a",0,1) -> 16358 | C1439: Tyler Mahle | D1439: CIN | E1439: 24 | F1439: 34 | G1439: 0 | H1439: 0 | I1439: 0 | J1439: 0 | K1439: 0.059 | L1439: 0.294 | M1439: 0.034 | N1439: 0.158 | O1439: 0.103 | P1439: 0.161 | Q1439: 0.138 | R1439: 0.141 | S1439: 0.169 | T1439: -22 | U1439: -0.2 | V1439: -5.3 | W1439: 4.1 | X1439: 0
A1440: 2018 | B1440: =_xlfn.XLOOKUP(C1440,ID!$J$2:$J$3825,ID!$I$2:$I$3825,"n/a",0,1) -> n/a | C1440: Michael Soroka | D1440: ATL | E1440: 5 | F1440: 8 | G1440: 0 | H1440: 0 | I1440: 0 | J1440: 0 | K1440: 0 | L1440: 0.125 | M1440: 0 | N1440: 0.143 | O1440: 0.125 | P1440: 0.125 | Q1440: 0.125 | R1440: 0.11 | S1440: 0.214 | T1440: -43 | U1440: 0 | V1440: -1.4 | W1440: 1 | X1440: 0
A1441: 2018 | B1441: =_xlfn.XLOOKUP(C1441,ID!$J$2:$J$3825,ID!$I$2:$I$3825,"n/a",0,1) -> 17192 | C1441: Jalen Beeks | D1441: 2 Tms | E1441: 14 | F1441: 2 | G1441: 0 | H1441: 0 | I1441: 0 | J1441: 0 | K1441: 0 | L1441: 0.5 | M1441: 0 | N1441: 0 | O1441: 0 | P1441: 0 | Q1441: 0 | R1441: 0 | S1441: 0.024 | T1441: -100 | U1441: 0 | V1441: -0.5 | W1441: 0.2 | X1441: 0
A1442: 2018 | B1442: =_xlfn.XLOOKUP(C1442,ID!$J$2:$J$3825,ID!$I$2:$I$3825,"n/a",0,1) -> n/a | C1442: Brett Graves | D1442: MIA | E1442: 21 | F1442: 2 | G1442: 0 | H1442: 0 | I1442: 0 | J1442: 0 | K1442: 0 | L1442: 0.5 | M1442: 0 | N1442: 0 | O1442: 0 | P1442: 0 | Q1442: 0 | R1442: 0 | S1442: 0 | T1442: -100 | U1442: 0 | V1442: -0.5 | W1442: 0.2 | X1442: 0
A1443: 2018 | B1443: =_xlfn.XLOOKUP(C1443,ID!$J$2:$J$3825,ID!$I$2:$I$3825,"n/a",0,1) -> n/a | C1443: Drew Gagnon | D1443: NYM | E1443: 5 | F1443: 2 | G1443: 0 | H1443: 0 | I1443: 1 | J1443: 0 | K1443: 0 | L1443: 0 | M1443: 0 | N1443: 0 | O1443: 0 | P1443: 0 | Q1443: 0 | R1443: 0 | S1443: 0.201 | T1443: -100 | U1443: 0 | V1443: -0.5 | W1443: 0.2 | X1443: 0
A1444: 2018 | B1444: =_xlfn.XLOOKUP(C1444,ID!$J$2:$J$3825,ID!$I$2:$I$3825,"n/a",0,1) -> n/a | C1444: Tim Peterson | D1444: NYM | E1444: 22 | F1444: 2 | G1444: 0 | H1444: 0 | I1444: 0 | J1444: 0 | K1444: 0 | L1444: 0.5 | M1444: 0 | N1444: 0 | O1444: 0 | P1444: 0 | Q1444: 0 | R1444: 0 | S1444: 0.24 | T1444: -100 | U1444: 0 | V1444: -0.5 | W1444: 0.2 | X1444: 0
... A1447: 2018 | B1447: =_xlfn.XLOOKUP(C1447,ID!$J$2:$J$3825,ID!$I$2:$I$3825,"n/a",0,1) -> n/a | C1447: Yairo Muñoz | D1447: STL | E1447: 108 | F1447: 329 | G1447: 8 | H1447: 39 | I1447: 42 | J1447: 5 | K1447: 0.091 | L1447: 0.216 | M1447: 0.137 | N1447: 0.338 | O1447: 0.276 | P1447: 0.35 | Q1447: 0.413 | R1447: 0.326 | S1447: 0.297 | T1447: 107 | U1447: -1.6 | V1447: 1.1 | W1447: -11.4 | X1447: 0
A1448: 2018 | B1448: =_xlfn.XLOOKUP(C1448,ID!$J$2:$J$3825,ID!$I$2:$I$3825,"n/a",0,1) -> 5257 | C1448: Wilmer Font | D1448: 3 Tms | E1448: 19 | F1448: 2 | G1448: 0 | H1448: 0 | I1448: 0 | J1448: 0 | K1448: 0 | L1448: 0 | M1448: 0 | N1448: 0 | O1448: 0 | P1448: 0 | Q1448: 0 | R1448: 0 | T1448: -100 | U1448: 0 | V1448: -0.5 | W1448: 0.2 | X1448: 0
A1449: 2018 | B1449: =_xlfn.XLOOKUP(C1449,ID!$J$2:$J$3825,ID!$I$2:$I$3825,"n/a",0,1) -> 16207 | C1449: Spencer Turnbull | D1449: DET | E1449: 4 | F1449: 2 | G1449: 0 | H1449: 0 | I1449: 0 | J1449: 0 | K1449: 0 | L1449: 0.5 | M1449: 0 | N1449: 0 | O1449: 0 | P1449: 0 | Q1449: 0 | R1449: 0 | S1449: 0.021 | T1449: -100 | U1449: 0 | V1449: -0.5 | W1449: 0.2 | X1449: 0
A1450: 2018 | B1450: =_xlfn.XLOOKUP(C1450,ID!$J$2:$J$3825,ID!$I$2:$I$3825,"n/a",0,1) -> n/a | C1450: Roberto Gómez | D1450: SFG | E1450: 5 | F1450: 2 | G1450: 0 | H1450: 0 | I1450: 0 | J1450: 0 | K1450: 0 | L1450: 1 | M1450: 0 | N1450: 0 | O1450: 0 | P1450: 0 | Q1450: 0 | R1450: 0 | S1450: 0 | T1450: -100 | U1450: 0 | V1450: -0.5 | W1450: 0.2 | X1450: 0
A1451: 2018 | B1451: =_xlfn.XLOOKUP(C1451,ID!$J$2:$J$3825,ID!$I$2:$I$3825,"n/a",0,1) -> 16981 | C1451: Tyler Beede | D1451: SFG | E1451: 2 | F1451: 2 | G1451: 0 | H1451: 0 | I1451: 0 | J1451: 0 | K1451: 0 | L1451: 1 | M1451: 0 | N1451: 0 | O1451: 0 | P1451: 0 | Q1451: 0 | R1451: 0 | S1451: 0 | T1451: -100 | U1451: 0 | V1451: -0.5 | W1451: 0.2 | X1451: 0
A1452: 2018 | B1452: =_xlfn.XLOOKUP(C1452,ID!$J$2:$J$3825,ID!$I$2:$I$3825,"n/a",0,1) -> 13228 | C1452: Michael Reed | D1452: ATL | E1452: 7 | F1452: 7 | G1452: 0 | H1452: 1 | I1452: 0 | J1452: 0 | K1452: 0 | L1452: 0.429 | M1452: 0 | N1452: 0.5 | O1452: 0.286 | P1452: 0.286 | Q1452: 0.286 | R1452: 0.251 | S1452: 0.391 | T1452: 51 | U1452: 0 | V1452: -0.4 | W1452: 0 | X1452: 0
A1453: 2018 | B1453: =_xlfn.XLOOKUP(C1453,ID!$J$2:$J$3825,ID!$I$2:$I$3825,"n/a",0,1) -> 15846 | C1453: Adam Plutko | D1453: CLE | E1453: 17 | F1453: 2 | G1453: 0 | H1453: 0 | I1453: 0 | J1453: 0 | K1453: 0 | L1453: 0 | M1453: 0 | N1453: 0 | O1453: 0 | P1453: 0 | Q1453: 0 | R1453: 0 | T1453: -100 | U1453: 0 | V1453: -0.5 | W1453: 0.2 | X1453: 0
A1454: 2018 | B1454: =_xlfn.XLOOKUP(C1454,ID!$J$2:$J$3825,ID!$I$2:$I$3825,"n/a",0,1) -> 11209 | C1454: Casey Sadler | D1454: PIT | E1454: 2 | F1454: 2 | G1454: 0 | H1454: 0 | I1454: 0 | J1454: 0 | K1454: 0 | L1454: 0.5 | M1454: 0 | N1454: 0 | O1454: 0 | P1454: 0 | Q1454: 0 | R1454: 0 | S1454: 0.081 | T1454: -100 | U1454: 0 | V1454: -0.5 | W1454: 0.2 | X1454: 0
A1455: 2018 | B1455: =_xlfn.XLOOKUP(C1455,ID!$J$2:$J$3825,ID!$I$2:$I$3825,"n/a",0,1) -> n/a | C1455: Richard Rodríguez | D1455: PIT | E1455: 63 | F1455: 2 | G1455: 0 | H1455: 0 | I1455: 0 | J1455: 0 | K1455: 0 | L1455: 1 | M1455: 0 | N1455: 0 | O1455: 0 | P1455: 0 | Q1455: 0 | R1455: 0 | S1455: 0 | T1455: -100 | U1455: 0 | V1455: -0.5 | W1455: 0.2 | X1455: 0
A1456: 2018 | B1456: =_xlfn.XLOOKUP(C1456,ID!$J$2:$J$3825,ID!$I$2:$I$3825,"n/a",0,1) -> n/a | C1456: Alex McRae | D1456: PIT | E1456: 2 | F1456: 2 | G1456: 0 | H1456: 0 | I1456: 0 | J1456: 0 | K1456: 0 | L1456: 0 | M1456: 0 | N1456: 0 | O1456: 0 | P1456: 0 | Q1456: 0 | R1456: 0 | S1456: 0.413 | T1456: -100 | U1456: 0 | V1456: -0.5 | W1456: 0.2 | X1456: 0
A1457: 2018 | B1457: =_xlfn.XLOOKUP(C1457,ID!$J$2:$J$3825,ID!$I$2:$I$3825,"n/a",0,1) -> n/a | C1457: Justin Hancock | D1457: CHC | E1457: 10 | F1457: 2 | G1457: 0 | H1457: 0 | I1457: 0 | J1457: 0 | K1457: 0 | L1457: 1 | M1457: 0 | N1457: 0 | O1457: 0 | P1457: 0 | Q1457: 0 | R1457: 0 | S1457: 0 | T1457: -100 | U1457: 0 | V1457: -0.5 | W1457: 0.2 | X1457: 0
A1458: 2018 | B1458: =_xlfn.XLOOKUP(C1458,ID!$J$2:$J$3825,ID!$I$2:$I$3825,"n/a",0,1) -> 16904 | C1458: Aaron Wilkerson | D1458: MIL | E1458: 3 | F1458: 2 | G1458: 0 | H1458: 0 | I1458: 0 | J1458: 0 | K1458: 0 | L1458: 0.5 | M1458: 0 | N1458: 0 | O1458: 0 | P1458: 0 | Q1458: 0 | R1458: 0 | S1458: 0.039 | T1458: -100 | U1458: 0 | V1458: -0.5 | W1458: 0.2 | X1458: 0
A1459: 2018 | B1459: =_xlfn.XLOOKUP(C1459,ID!$J$2:$J$3825,ID!$I$2:$I$3825,"n/a",0,1) -> 15490 | C1459: Justin Williams | D1459: TBR | E1459: 1 | F1459: 1 | G1459: 0 | H1459: 0 | I1459: 0 | J1459: 0 | K1459: 0 | L1459: 0 | M1459: 0 | N1459: 0 | O1459: 0 | P1459: 0 | Q1459: 0 | R1459: 0 | S1459: 0.123 | T1459: -100 | U1459: 0 | V1459: -0.3 | W1459: 0 | X1459: 0
A1460: 2018 | B1460: =_xlfn.XLOOKUP(C1460,ID!$J$2:$J$3825,ID!$I$2:$I$3825,"n/a",0,1) -> 15047 | C1460: Austin Voth | D1460: WSN | E1460: 4 | F1460: 2 | G1460: 0 | H1460: 0 | I1460: 0 | J1460: 0 | K1460: 0 | L1460: 0.5 | M1460: 0 | N1460: 0 | O1460: 0 | P1460: 0 | Q1460: 0 | R1460: 0 | S1460: 0.066 | T1460: -100 | U1460: 0 | V1460: -0.5 | W1460: 0.2 | X1460: 0
A1461: 2018 | B1461: =_xlfn.XLOOKUP(C1461,ID!$J$2:$J$3825,ID!$I$2:$I$3825,"n/a",0,1) -> n/a | C1461: Kyle McGowin | D1461: WSN | E1461: 5 | F1461: 2 | G1461: 0 | H1461: 1 | I1461: 0 | J1461: 0 | K1461: 0 | L1461: 0 | M1461: 0 | N1461: 0 | O1461: 0 | P1461: 0 | Q1461: 0 | R1461: 0 | S1461: 0.048 | T1461: -100 | U1461: 0 | V1461: -0.5 | W1461: 0.2 | X1461: 0
A1462: 2018 | B1462: =_xlfn.XLOOKUP(C1462,ID!$J$2:$J$3825,ID!$I$2:$I$3825,"n/a",0,1) -> 11241 | C1462: Mike Freeman | D1462: CHC | E1462: 1 | F1462: 1 | G1462: 0 | H1462: 0 | I1462: 0 | J1462: 0 | K1462: 0 | L1462: 0 | M1462: 0 | N1462: 0 | O1462: 0 | P1462: 0 | Q1462: 0 | R1462: 0 | T1462: -100 | U1462: 0 | V1462: -0.3 | W1462: 0 | X1462: 0
...

Sheet ID
A1: IDPLAYER | B1: PLAYERNAME | C1: BIRTHDATE | D1: FIRSTNAME | E1: LASTNAME | F1: TEAM | G1: LG | H1: POS | I1: IDFANGRAPHS | J1: FANGRAPHSNAME | K1: MLBID | L1: MLBNAME | M1: CBSID | N1: CBSNAME | O1: RETROID | P1: BREFID | Q1: NFBCID | R1: NFBCNAME | S1: ESPNID | T1: ESPNNAME | U1: KFFLNAME | V1: DAVENPORTID | W1: BPID | X1: YAHOOID | Y1: YAHOONAME | Z1: MSTRBLLNAME | AA1: BATS | AB1: THROWS | AC1: FANTPROSNAME | AD1: LASTCOMMAFIRST | AE1: ROTOWIREID | AF1: FANDUELNAME | AG1: FANDUELID | AH1: DRAFTKINGSNAME | AI1: OTTONEUID | AJ1: HQID | AK1: RAZZBALLNAME | AL1: FANTRAXID | AM1: FANTRAXNAME | AN1: ROTOWIRENAME | AO1: ALLPOS | AP1: NFBCLASTFIRST | AQ1: ACTIVE | AR1: UNDERDOG | AS1: RAZZBALLID
A2: aardsda01 | B2: David Aardsma | C2: 29947 | D2: David | E2: Aardsma | F2: N/A | G2: N/A | H2: P | I2: 1902 | J2: David Aardsma | K2: 430911 | L2: David Aardsma | M2: 479025 | N2: David Aardsma | O2: aardd001 | P2: aardsda01 | R2: David Aardsma | S2: 5933 | T2: David Aardsma | V2: AARDSMA19811227A | W2: 45369 | X2: 7307 | Y2: David Aardsma | Z2: Aardsma, David | AA2: R | AB2: R | AC2: David Aardsma | AD2: Aardsma, David | AE2: 7633 | AH2: David Aardsma | AI2: 4362 | AK2: David Aardsma | AM2: David Aardsma | AN2: David Aardsma | AO2: P | AP2: Aardsma, David | AQ2: N
A3: abadfe01 | B3: Fernando Abad | C3: 31398 | D3: Fernando | E3: Abad | F3: COL | G3: NL | H3: P | I3: 4994 | J3: Fernando Abad | K3: 472551 | L3: Fernando Abad | M3: 1723564 | N3: Fernando Abad | O3: abadf001 | P3: abadfe01 | Q3: 7932 | R3: Fernando Abad | S3: 30417 | T3: Fernando Abad | V3: ABAD19851217A | W3: 49706 | X3: 8767 | Y3: Fernando Abad | Z3: Abad, Fernando | AA3: L | AB3: L | AC3: Fernando Abad | AD3: Abad, Fernando | AE3: 11285 | AF3: Fernando Abad | AG3: 12453 | AH3: Fernando Abad | AI3: 7372 | AJ3: 3556 | AK3: Fernando Abad | AL3: *01viz* | AM3: Fernando Abad | AN3: Fernando Abad | AO3: P | AP3: Abad, Fernando | AQ3: N | AR3: 344ab5df-3d83-410a-9ba7-76f12fc69779 | AS3: 4994
A4: abbotan01 | B4: Andrew Abbott | C4: 36312 | D4: Andrew | E4: Abbott | F4: CIN | G4: NL | H4: P | I4: 29911 | J4: Andrew Abbott | K4: 671096 | L4: Andrew Abbott | M4: 2836515 | N4: Andrew Abbott | O4: abboa001 | P4: abbotan01 | Q4: 11802 | R4: Andrew Abbott | S4: 4414528 | T4: Andrew Abbott | V4: ABBOTT19990601A | W4: 111327 | X4: 12395 | Y4: Andrew Abbott | AA4: L | AB4: L | AC4: Andrew Abbott | AD4: Abbott, Andrew | AE4: 16805 | AI4: 40607 | AJ4: 7179 | AK4: Andrew Abbott | AL4: *05jq2* | AM4: Andrew Abbott | AN4: Andrew Abbott | AO4: SP | AP4: Abbott, Andrew | AQ4: Y | AR4: 8b1f18bf-f4ec-4de5-876a-9e38f533601a | AS4: 671096
A5: abbotco01 | B5: Cory Abbott | C5: 34962 | D5: Cory | E5: Abbott | F5: SEA | G5: AL | H5: P | I5: 20277 | J5: Cory Abbott | K5: 676265 | L5: Cory Abbott | M5: 3116181 | N5: Cory Abbott | O5: abboc001 | P5: abbotco01 | Q5: 10790 | R5: Cory Abbott | S5: 41328 | T5: Cory Abbott | V5: ABBOTT19950920A | W5: 111166 | X5: 11435 | Y5: Cory Abbott | Z5: Abbott, Cory | AA5: R | AB5: R | AC5: Cory Abbott | AD5: Abbott, Cory | AE5: 14996 | AI5: 27184 | AJ5: 6286 | AK5: Cory Abbott | AL5: *04ef6* | AM5: Cory Abbott | AN5: Cory Abbott | AO5: P | AP5: Abbott, Cory | AQ5: Y | AR5: cc172e35-3d27-41ef-b65e-b37d9635deae | AS5: 676265
A6: abelmi01 | B6: Mick Abel | C6: 37121 | D6: Mick | E6: Abel | F6: MIN | G6: AL | H6: P | I6: 27756 | J6: Mick Abel | K6: 690953 | L6: Mick Abel | M6: 26615392 | N6: Mick Abel | O6: abelm001 | P6: abelmi01 | Q6: 11632 | R6: Mick Abel | S6: 4718970 | T6: Mick Abel | V6: ABEL20010818A | W6: 147751 | X6: 12166 | Y6: Mick Abel | AA6: R | AB6: R | AC6: Mick Abel | AD6: Abel, Mick | AE6: 16679 | AI6: 38330 | AJ6: 7268 | AK6: Mick Abel | AL6: *05g4k* | AM6: Mick Abel | AN6: Mick Abel | AO6: P | AP6: Abel, Mick | AQ6: Y | AR6: 6151ffe0-7851-4593-9466-e1b0b8b4bad4 | AS6: 690953
A7: abramcj01 | B7: CJ Abrams | C7: 36802 | D7: CJ | E7: Abrams | F7: WAS | G7: NL | H7: SS | I7: 25768 | J7: CJ Abrams | K7: 682928 | L7: CJ Abrams | M7: 3117475 | N7: C.J. Abrams | O7: abrac001 | P7: abramcj01 | Q7: 11045 | R7: CJ Abrams | S7: 42402 | T7: CJ Abrams | V7: ABRAMS20001003A | W7: 111352 | X7: 11822 | Y7: CJ Abrams | Z7: Abrams, CJ | AA7: L | AB7: R | AC7: CJ Abrams | AD7: Abrams, CJ | AE7: 16042 | AI7: 36922 | AJ7: 6791 | AK7: CJ Abrams | AL7: *04qk8* | AM7: CJ Abrams | AN7: CJ Abrams | AO7: SS | AP7: Abrams, CJ | AQ7: Y | AR7: beec0d4a-ed73-489b-80f1-3b811a071db9 | AS7: 682928
A8: abreual01 | B8: Albert Abreu | C8: 34968 | D8: Albert | E8: Abreu | F8: CIN | G8: NL | H8: SS | I8: 17485 | J8: Albert Abreu | K8: 656061 | L8: Albert Abreu | M8: 2211792 | N8: Albert Abreu | O8: abrea001 | P8: abreual01 | Q8: 9895 | R8: Albert Abreu | S8: 36041 | T8: Albert Abreu | V8: ABREU19950926A | W8: 104651 | X8: 10546 | Y8: Albert Abreu | Z8: Abreu, Albert | AA8: R | AB8: R | AC8: Albert Abreu | AD8: Abreu, Albert | AE8: 14063 | AI8: 20720 | AJ8: 5762 | AK8: Albert Abreu | AL8: *03xy4* | AM8: Albert Abreu | AN8: Albert Abreu | AO8: SS | AP8: Abreu, Albert | AQ8: Y | AR8: 1ca19d52-0c24-499a-8138-9410db0d8c58
A9: abreubo01 | B9: Bobby Abreu | C9: 27099 | D9: Bobby | E9: Abreu | F9: N/A | G9: N/A | H9: OF | I9: 945 | J9: Bobby Abreu | K9: 110029 | L9: Bobby Abreu | M9: 7367 | N9: Bobby Abreu | O9: abreb001 | P9: abreubo01 | R9: Bobby Abreu | S9: 3537 | T9: Bobby Abreu | U9: Bobby Abreu | V9: ABREU19740311A | W9: 650 | X9: 5698 | Y9: Bobby Abreu | Z9: Abreu, Bobby | AA9: L | AB9: R | AC9: Bobby Abreu | AD9: Abreu, Bobby | AI9: 8984 | AK9: Bobby Abreu | AM9: Bobby Abreu | AN9: Bobby Abreu | AO9: OF | AP9: Abreu, Bobby | AQ9: N
A10: abreubr01 | B10: Bryan Abreu | C10: 35542 | D10: Bryan | E10: Abreu | F10: HOU | G10: AL | H10: P | I10: 16609 | J10: Bryan Abreu | K10: 650556 | L10: Bryan Abreu | M10: 3055522 | N10: Bryan Abreu | O10: abreb002 | P10: abreubr01 | Q10: 10381 | R10: Bryan Abreu | S10: 41208 | T10: Bryan Abreu | V10: ABREU19970422A | W10: 104258 | X10: 11208 | Y10: Bryan Abreu | Z10: Abreu, Bryan | AA10: R | AB10: R | AC10: Bryan Abreu | AD10: Abreu, Bryan | AE10: 15744 | AI10: 20900 | AJ10: 6034 | AK10: Bryan Abreu | AL10: *04tlv* | AM10: Bryan Abreu | AN10: Bryan Abreu | AO10: RP | AP10: Abreu, Bryan | AQ10: Y | AR10: 89da4ba9-7145-40d7-8d7d-8064ce33b3e2 | AS10: 650556
A11: abreujo02 | B11: Jose Abreu | C11: 31806 | D11: Jose | E11: Abreu | F11: N/A | G11: N/A | H11: 1B | I11: 15676 | J11: Jose Abreu | K11: 547989 | L11: Jose Abreu | M11: 2106364 | N11: Jose Abreu | O11: abrej003 | P11: abreujo02 | Q11: 8626 | R11: Jose Abreu | S11: 33095 | T11: Jose Abreu | U11: Jose Abreu | V11: ABREUcubaJ01 | W11: 102005 | X11: 9540 | Y11: Jose Abreu | Z11: Abreu, Jose | AA11: R | AB11: R | AC11: Jose Abreu | AD11: Abreu, Jose | AE11: 11341 | AF11: Jose Abreu | AG11: 49523 | AH11: Jose Abreu | AI11: 18286 | AJ11: 4515 | AK11: Jose Abreu | AL11: *02i2e* | AM11: Jose Abreu | AN11: Jose Abreu | AO11: 1B | AP11: Abreu, Jose | AQ11: N | AR11: c57d78f5-d6fe-4369-8aa0-a9e68a4d2084 | AS11: 15676
A12: abreuto01 | B12: Tony Abreu | C12: 30999 | D12: Tony | E12: Abreu | F12: N/A | G12: N/A | H12: 2B | I12: 5053 | J12: Tony Abreu | K12: 473234 | L12: Tony Abreu | M12: 593265 | N12: Tony Abreu | O12: abret001 | P12: abreuto01 | R12: Tony Abreu | S12: 28777 | T12: Tony Abreu | U12: Tony Abreu | V12: ABREU19841113A | W12: 46923 | X12: 8033 | Y12: Tony Abreu | Z12: Abreu, Tony | AA12: B | AB12: R | AC12: Tony Abreu | AD12: Abreu, Tony | AE12: 9244 | AI12: 549 | AK12: Tony Abreu | AL12: *0002e* | AM12: Tony Abreu | AN12: Tony Abreu | AO12: 2B | AP12: Abreu, Tony | AQ12: N
A13: abreuwi02 | B13: Wilyer Abreu | C13: 36335 | D13: Wilyer | E13: Abreu | F13: BOS | G13: AL | H13: OF | I13: 23772 | J13: Wilyer Abreu | K13: 677800 | L13: Wilyer Abreu | M13: 28838043 | N13: Wilyer Abreu | O13: abrew002 | P13: abreuwi02 | Q13: 11709 | R13: Wilyer Abreu | S13: 4990055 | T13: Wilyer Abreu | V13: ABREU19990624A | W13: 111086 | X13: 12731 | Y13: Wilyer Abreu | AA13: L | AB13: L | AC13: Wilyer Abreu | AD13: Abreu, Wilyer | AE13: 17794 | AI13: 27058 | AJ13: 7815 | AK13: Wilyer Abreu | AL13: *060x1* | AM13: Wilyer Abreu | AN13: Wilyer Abreu | AO13: OF | AP13: Abreu, Wilyer | AQ13: Y | AR13: d8928609-98b5-45f8-80ef-b90c5c6b27f8 | AS13: 677800
A14: accarje01 | B14: Jeremy Accardo | C14: 29938 | D14: Jeremy | E14: Accardo | F14: N/A | G14: N/A | H14: P | I14: 6428 | J14: Jeremy Accardo | K14: 435618 | L14: Jeremy Accardo | M14: 490429 | N14: Jeremy Accardo | O14: accaj001 | P14: accarje01 | R14: Jeremy Accardo | S14: 6262 | T14: Jeremy Accardo | V14: ACCARDO19811208A | W14: 45614 | X14: 7534 | Y14: Jeremy Accardo | Z14: Accardo, Jeremy | AA14: R | AB14: R | AC14: Jeremy Accardo | AD14: Accardo, Jeremy | AI14: 8034 | AK14: Jeremy Accardo | AL14: *000ge* | AM14: Jeremy Accardo | AN14: Jeremy Accardo | AO14: P | AP14: Accardo, Jeremy | AQ14: N
A15: aceveal01 | B15: Alfredo Aceves | C15: 30293 | D15: Alfredo | E15: Aceves | F15: N/A | G15: N/A | H15: P | I15: 5164 | J15: Alfredo Aceves | K15: 469686 | L15: Alfredo Aceves | M15: 1638980 | N15: Alfredo Aceves | O15: aceva001 | P15: aceveal01 | R15: Alfredo Aceves | S15: 29223 | T15: Alfredo Aceves | V15: ACEVES19821208A | W15: 46928 | X15: 8336 | Y15: Alfredo Aceves | Z15: Aceves, Alfredo | AA15: R | AB15: R | AC15: Alfredo Aceves | AD15: Aceves, Alfredo | AE15: 10464 | AI15: 580 | AK15: Alfredo Aceves | AM15: Alfredo Aceves | AN15: Alfredo Aceves | AO15: P | AP15: Aceves, Alfredo | AQ15: N
A16: acevedo01 | B16: Domingo Acevedo | C16: 34399 | D16: Domingo | E16: Acevedo | F16: ATH | G16: AL | H16: P | I16: 17092 | J16: Domingo Acevedo | K16: 642758 | L16: Domingo Acevedo | M16: 2211789 | N16: Domingo Acevedo | O16: acevd001 | P16: acevedo01 | Q16: 9896 | R16: Domingo Acevedo | S16: 35010 | T16: Domingo Acevedo | V16: ACEVEDO19940603A | W16: 103250 | X16: 10545 | Y16: Domingo Acevedo | Z16: Acevedo, Domingo | AA16: R | AB16: R | AC16: Domingo Acevedo | AD16: Acevedo, Domingo | AE16: 14060 | AI16: 20032 | AJ16: 5763 | AK16: Domingo Acevedo | AL16: *03bam* | AM16: Domingo Acevedo | AN16: Domingo Acevedo | AO16: P | AP16: Acevedo, Domingo | AQ16: Y | AR16: af1275bf-b16e-4329-83de-383bea6c3c32 | AS16: 642758
A17: ackledu01 | B17: Dustin Ackley | C17: 32199 | D17: Dustin | E17: Ackley | F17: SEA | G17: AL | H17: 1B | I17: 10099 | J17: Dustin Ackley | K17: 554429 | L17: Dustin Ackley | M17: 1699742 | N17: Dustin Ackley | O17: ackld001 | P17: ackledu01 | R17: Dustin Ackley | S17: 30372 | T17: Dustin Ackley | U17: Dustin Ackley | V17: ACKLEY19880226A | W17: 61057 | X17: 8648 | Y17: Dustin Ackley | Z17: Ackley, Dustin | AA17: L | AB17: R | AC17: Dustin Ackley | AD17: Ackley, Dustin | AE17: 10944 | AF17: Dustin Ackley | AG17: 12853 | AH17: Dustin Ackley | AI17: 5141 | AJ17: 3375 | AK17: Dustin Ackley | AL17: *01fhn* | AM17: Dustin Ackley | AN17: Dustin Ackley | AO17: 1B | AP17: Ackley, Dustin | AQ17: N
A18: acostma01 | B18: Maximo Acosta | C18: 37558 | D18: Maximo | E18: Acosta | F18: MIA | G18: NL | H18: SS | I18: 27963 | J18: Maximo Acosta | K18: 691185 | L18: Maximo Acosta | N18: Maximo Acosta | O18: acosm001 | P18: acostma02 | Q18: 12290 | R18: Maximo Acosta | T18: Maximo Acosta | V18: ACOSTA20021029A | Y18: Maximo Acosta | Z18: Maximo Acosta | AA18: R | AB18: R | AC18: Maximo Acosta | AD18: Acosta, Maximo | AE18: 16348 | AF18: Maximo Acosta | AH18: Maximo Acosta | AJ18: 8381 | AK18: Maximo Acosta | AL18: *0568a* | AM18: Maximo Acosta | AN18: Maximo Acosta | AO18: SS | AP18: Acosta, Maximo | AQ18: Y | AR18: d9be8c85-21f4-4798-8df9-fca8d5724f6e | AS18: 691185
A19: actonga01 | B19: Garrett Acton | C19: 35961 | D19: Garrett | E19: Acton | F19: TB | G19: AL | H19: P | I19: 27583 | J19: Garrett Acton | K19: 670183 | L19: Garrett Acton | M19: 29084569 | N19: Garrett Acton | O19: actog001 | P19: actonga01 | Q19: 11759 | R19: Garrett Acton | S19: 4424444 | T19: Garrett Acton | V19: ACTON19980615A | W19: 111459 | X19: 61900 | Y19: Garrett Acton | AA19: L | AB19: R | AC19: Garrett Acton | AD19: Acton, Garrett | AE19: 17058 | AI19: 38539 | AJ19: 7318 | AK19: Garrett Acton | AL19: *05ybh* | AM19: Garrett Acton | AN19: Garrett Acton | AO19: P | AP19: Acton, Garrett | AQ19: Y | AR19: 6a08077a-df3d-45c9-a1b2-68e55049328b | AS19: 670183
A20: acunalu01 | B20: Luisangel Acuna | C20: 37327 | D20: Luisangel | E20: Acuna | F20: NYM | G20: NL | H20: SS | I20: 26548 | J20: Luisangel Acuna | K20: 682668 | L20: Luisangel Acuna | M20: 26615344 | N20: Luisangel Acuna | O20: acunl001 | P20: acunajo01 | Q20: 11614 | R20: Luisangel Acuna | T20: Luisangel Acuna | V20: ACUNA20020312A | W20: 111462 | Y20: Luisangel Acuna | AA20: R | AB20: R | AC20: Luisangel Acuna | AD20: Acuna, Luisangel | AE20: 16302 | AI20: 36048 | AJ20: 7855 | AK20: Luisangel Acuna | AL20: *04z6k* | AM20: Luisangel Jose Acuna | AN20: Luisangel Acuna | AO20: SS | AP20: Acuna, Luisangel | AQ20: Y | AR20: eaad3760-3954-4c5d-a82b-63983fed1f4c | AS20: 682668
A21: acunaro01 | B21: Ronald Acuna | C21: 35782 | D21: Ronald | E21: Acuna | F21: ATL | G21: NL | H21: OF | I21: 18401 | J21: Ronald Acuna Jr. | K21: 660670 | L21: Ronald Acuna | M21: 2211777 | N21: Ronald Acuna | O21: acunr001 | P21: acunaro01 | Q21: 9775 | R21: Ronald Acuna Jr. | S21: 36185 | T21: Ronald Acuna | V21: ACUNA19971218A | W21: 105454 | X21: 10646 | Y21: Ronald Acuna Jr. | Z21: Acuna Jr., Ronald | AA21: R | AB21: R | AC21: Ronald Acuna Jr. | AD21: Acuna, Ronald | AE21: 14200 | AI21: 23327 | AJ21: 5588 | AK21: Ronald Acuna Jr. | AL21: *03wha* | AM21: Ronald Acuna Jr. | AN21: Ronald Acuna | AO21: OF | AP21: Acuna Jr., Ronald | AQ21: Y | AR21: 0313642a-1e49-4c9f-8daa-79f2f440865d | AS21: 660670
A22: adamecr01 | B22: Cristhian Adames | C22: 33445 | D22: Cristhian | E22: Adames | F22: SF | G22: NL | H22: 2B | I22: 6013 | J22: Cristhian Adames | K22: 542436 | L22: Cristhian Adames | M22: 1959299 | N22: Cristhian Adames | O22: adamc001 | P22: adamecr01 | Q22: 8855 | R22: Cristhian Adames | S22: 31659 | T22: Cristhian Adames | V22: ADAMES19910726A | W22: 59755 | X22: 9774 | Y22: Cristhian Adames | Z22: Adames, Cristhian | AA22: B | AB22: R | AC22: Cristhian Adames | AD22: Adames, Cristhian | AE22: 11817 | AF22: Cristhian Adames | AG22: 21582 | AH22: Cristhian Adames | AI22: 10307 | AJ22: 4701 | AK22: Cristhian Adames | AL22: *027j7* | AM22: Cristhian Adames | AN22: Cristhian Adames | AO22: 2B | AP22: Adames, Cristhian | AQ22: N
A23: adamewi01 | B23: Willy Adames | C23: 34944 | D23: Willy | E23: Adames | F23: SF | G23: NL | H23: SS | I23: 15986 | J23: Willy Adames | K23: 642715 | L23: Willy Adames | M23: 2165933 | N23: Willy Adames | O23: adamw002 | P23: adamewi01 | Q23: 8971 | R23: Willy Adames | S23: 33675 | T23: Willy Adames | V23: ADAMES19950902A | W23: 103209 | X23: 9893 | Y23: Willy Adames | Z23: Adames, Willy | AA23: R | AB23: R | AC23: Willy Adames | AD23: Adames, Willy | AE23: 13593 | AH23: Willy Adames | AI23: 18407 | AJ23: 5053 | AK23: Willy Adames | AL23: *03atq* | AM23: Willy Adames | AN23: Willy Adames | AO23: SS | AP23: Adames, Willy | AQ23: Y | AR23: 6eb26750-b70f-4aa0-9f5f-da18f81f6d4b | AS23: 642715
A24: adamja01 | B24: Jason Adam | C24: 33454 | D24: Jason | E24: Adam | F24: SD | G24: NL | H24: P | I24: 11861 | J24: Jason Adam | K24: 592094 | L24: Jason Adam | M24: 1846226 | N24: Jason Adam | O24: adamj002 | P24: adamja01 | Q24: 10025 | R24: Jason Adam | S24: 32145 | T24: Jason Adam | V24: ADAM19910804A | W24: 68490 | X24: 11009 | Y24: Jason Adam | Z24: Adam, Jason | AA24: R | AB24: R | AC24: Jason Adam | AD24: Adam, Jason | AE24: 11588 | AF24: Jason Adam | AH24: Jason Adam | AI24: 27723 | AJ24: 5875 | AK24: Jason Adam | AL24: *025it* | AM24: Jason Adam | AN24: Jason Adam | AO24: RP | AP24: Adam, Jason | AQ24: Y | AR24: 54fad8c4-3974-4c09-99f6-c264e054dcd8 | AS24: 592094
A25: adamsau02 | B25: Austin Adams | C25: 33363 | D25: Austin | E25: Adams | F25: BOS | G25: AL | H25: P | I25: 13801 | J25: Austin Adams | K25: 613534 | L25: Austin Adams | M25: 2444539 | N25: Austin Adams | O25: adama002 | P25: adamsau02 | Q25: 9531 | R25: Austin Adams | S25: 31660 | T25: Austin Adams | V25: ADAMS19910505A | W25: 59978 | X25: 10760 | Y25: Austin L. Adams | Z25: Adams, Austin L. | AA25: R | AB25: R | AC25: Austin Adams | AD25: Adams, Austin | AE25: 14614 | AF25: Austin Adams | AH25: Austin Adams | AI25: 30529 | AJ25: 5652 | AK25: Austin Adams | AL25: *02h8x* | AM25: Austin Adams | AN25: Austin Adams | AO25: RP | AP25: Adams, Austin | AQ25: Y | AR25: 116527e4-cb64-4725-9210-9c0dd2d89b89 | AS25: 613534
A26: adamsch01 | B26: Chance Adams | C26: 34556 | D26: Chance | E26: Adams | F26: KC | G26: AL | H26: P | I26: 18135 | J26: Chance Adams | K26: 664856 | L26: Chance Adams | M26: 2449975 | N26: Chance Adams | O26: adamc002 | P26: adamsch01 | Q26: 9780 | R26: Chance Adams | S26: 36160 | T26: Chance Adams | V26: ADAMS19940810A | W26: 105455 | X26: 10541 | Y26: Chance Adams | Z26: Adams, Chance | AA26: R | AB26: R | AC26: Chance Adams | AD26: Adams, Chance | AE26: 14548 | AI26: 22738 | AJ26: 5647 | AK26: Chance Adams | AL26: *03qle* | AM26: Chance Adams | AN26: Chance Adams | AO26: P | AP26: Adams, Chance | AQ26: N | AS26: 664856
A27: adamsda02 | B27: David Adams | C27: 31912 | D27: David | E27: Adams | F27: N/A | G27: N/A | H27: 2B | I27: 7389 | J27: David Adams | K27: 458691 | L27: David Adams | M27: 1740903 | N27: David Adams | O27: adamd001 | P27: adamsda02 | R27: David Adams | S27: 30679 | T27: David Adams | U27: David Adams | V27: ADAMS19870515A | W27: 58003 | X27: 9395 | Y27: David Adams | Z27: Adams, David | AA27: R | AB27: R | AC27: David Adams | AD27: Adams, David | AE27: 10562 | AI27: 5335 | AK27: David Adams | AL27: *01sgs* | AM27: David Adams | AN27: David Adams | AO27: 2B | AP27: Adams, David | AQ27: N
A28: adamsla01 | B28: Lane Adams | C28: 32825 | D28: Lane | E28: Adams | F28: ATL | G28: NL | H28: OF | I28: 10767 | J28: Lane Adams | K28: 572669 | L28: Lane Adams | M28: 2048786 | N28: Lane Adams | O28: adaml001 | P28: adamsla01 | Q28: 8885 | R28: Lane Adams | S28: 32911 | T28: Lane Adams | V28: ADAMS19891113A | W28: 60150 | X28: 9806 | Y28: Lane Adams | Z28: Adams, Lane | AA28: R | AB28: R | AC28: Lane Adams | AD28: Adams, Lane | AE28: 13223 | AH28: Lane Adams | AI28: 12380 | AJ28: 4741 | AK28: Lane Adams | AL28: *02hce* | AM28: Lane Adams | AN28: Lane Adams | AO28: OF | AP28: Adams, Lane | AQ28: N
A29: adamsma01 | B29: Matt Adams | C29: 32386 | D29: Matt | E29: Adams | F29: WAS | G29: NL | H29: DH | I29: 9393 | J29: Matt Adams | K29: 571431 | L29: Matt Adams | M29: 1810388 | N29: Matt Adams | O29: adamm002 | P29: adamsma01 | Q29: 8214 | R29: Matt Adams | S29: 31359 | T29: Matt Adams | U29: Matt Adams | V29: ADAMS19880831A | W29: 59582 | X29: 9100 | Y29: Matt Adams | Z29: Adams, Matt | AA29: L | AB29: R | AC29: Matt Adams | AD29: Adams, Matt | AE29: 11977 | AF29: Matt Adams | AG29: 13799 | AH29: Matt Adams | AI29: 6302 | AJ29: 4003 | AK29: Matt Adams | AL29: *0272u* | AM29: Matt Adams | AN29: Matt Adams | AO29: DH | AP29: Adams, Matt | AQ29: N
A30: adamsmi03 | B30: Mike Adams | C30: 28700 | D30: Mike | E30: Adams | F30: N/A | G30: N/A | H30: P | I30: 1937 | J30: Mike Adams | K30: 430606 | L30: Mike Adams | M30: 392251 | N30: Mike Adams | O30: adamm102 | P30: adamsmi03 | R30: Mike Adams | S30: 5969 | T30: Mike Adams | V30: ADAMS19480724A | W30: 18328 | X30: 7332 | Y30: Mike Adams | Z30: Adams, Mike | AA30: R | AB30: R | AC30: Mike Adams | AD30: Adams, Mike | AI30: 3799 | AK30: Mike Adams | AL30: *005i9* | AM30: Mike Adams | AN30: Mike Adams | AO30: P | AP30: Adams, Mike | AQ30: N
A31: adamsri03 | B31: Riley Adams | C31: 35242 | D31: Riley | E31: Adams | F31: WAS | G31: NL | H31: C | I31: 19864 | J31: Riley Adams | K31: 656180 | L31: Riley Adams | M31: 2836521 | N31: Riley Adams | O31: adamr004 | P31: adamsri03 | Q31: 10850 | R31: Riley Adams | S31: 40655 | T31: Riley Adams | V31: ADAMS19960626A | W31: 109294 | X31: 11997 | Y31: Riley Adams | Z31: Adams, Riley | AA31: R | AB31: R | AC31: Riley Adams | AD31: Adams, Riley | AE31: 14832 | AI31: 31564 | AJ31: 6408 | AK31: Riley Adams | AL31: *04azt* | AM31: Riley Adams | AN31: Riley Adams | AO31: C | AP31: Adams, Riley | AQ31: Y | AR31: 571dd37a-6c05-460a-8c51-6f7508d080f0 | AS31: 656180
A32: adamssp03 | B32: Spencer Adams | C32: 35168 | D32: Spencer | E32: Adams | F32: CHW | G32: AL | H32: P | J32: Spencer Adams | K32: 656181 | L32: Spencer Adams | M32: 2167472 | N32: Spencer Adams | P32: adamssp03 | S32: 33779 | T32: Spencer Adams | V32: ADAMS19960413A | W32: 104717 | X32: 10449 | Y32: Spencer Adams | Z32: Adams, Spencer | AA32: R | AB32: R | AC32: Spencer Adams | AD32: Adams, Spencer | AE32: 13390 | AJ32: 6027 | AK32: Spencer Adams | AL32: *03d77* | AM32: Spencer Adams | AN32: Spencer Adams | AO32: P | AQ32: N
A33: adducji02 | B33: Jim Adduci | C33: 31182 | D33: Jim | E33: Adduci | F33: CHC | G33: NL | H33: OF | I33: 6448 | J33: Jim Adduci | K33: 451192 | L33: Jim Adduci | M33: 549732 | N33: Jim Adduci | O33: adduj002 | P33: adducji02 | Q33: 8597 | R33: Jim Adduci | S33: 30019 | T33: Jim Adduci | V33: ADDUCI19850515A | W33: 46943 | X33: 9512 | Y33: Jim Adduci | Z33: Adduci, Jim | AA33: L | AB33: L | AC33: Jim Adduci | AD33: Adduci, Jim | AE33: 11299 | AH33: Jim Adduci | AI33: 1672 | AJ33: 4456 | AK33: Jim Adduci | AL33: *037y7* | AM33: Jim Adduci | AN33: Jim Adduci | AO33: OF | AP33: Adduci, Jim | AQ33: N
A34: adelljo01 | B34: Jo Adell | C34: 36258 | D34: Jo | E34: Adell | F34: LAA | G34: AL | H34: OF | I34: 20220 | J34: Jo Adell | K34: 666176 | L34: Jo Adell | M34: 2835062 | N34: Jo Adell | O34: adelj001 | P34: adelljo01 | Q34: 10241 | R34: Jo Adell | S34: 40854 | T34: Jo Adell | V34: ADELL19990408A | W34: 109295 | X34: 10893 | Y34: Jo Adell | Z34: Adell, Jo | AA34: R | AB34: R | AC34: Jo Adell | AD34: Adell, Jo | AE34: 14770 | AH34: Jo Adell | AI34: 23792 | AJ34: 6082 | AK34: Jo Adell | AL34: *04aee* | AM34: Jo Adell | AN34: Jo Adell | AO34: OF | AP34: Adell, Jo | AQ34: Y | AR34: 273b8042-63e2-4675-956e-37305cdbe006 | AS34: 666176
A35: adlemti01 | B35: Tim Adleman | C35: 32094 | D35: Tim | E35: Adleman | F35: N/A | G35: N/A | H35: P | I35: 10968 | J35: Tim Adleman | K35: 534947 | L35: Tim Adleman | M35: 2170252 | N35: Tim Adleman | O35: adlet001 | P35: adlemti01 | Q35: 9356 | R35: Tim Adleman | S35: 33962 | T35: Tim Adleman | V35: ADLEMAN19871113A | W35: 65945 | X35: 10282 | Y35: Tim Adleman | Z35: Adleman, Tim | AA35: R | AB35: R | AC35: Timothy Adleman | AD35: Adleman, Tim | AE35: 14208 | AF35: Tim Adleman | AG35: 70351 | AH35: Tim Adleman | AI35: 13610 | AJ35: 5261 | AK35: Tim Adleman | AL35: *040kr* | AM35: Tim Adleman | AN35: Tim Adleman | AO35: P | AP35: Adleman, Tim | AQ35: N
A36: adonjo01 | B36: Joan Adon | C36: 36019 | D36: Joan | E36: Adon | F36: WAS | G36: NL | H36: P | I36: 22925 | J36: Joan Adon | K36: 672851 | L36: Joan Adon | M36: 2829294 | N36: Joan Adon | O36: adonj001 | P36: adonjo01 | Q36: 10968 | R36: Joan Adon | S36: 4684360 | T36: Joan Adon | V36: ADON19980812A | W36: 109297 | X36: 11857 | Y36: Joan Adon | Z36: Adon, Joan | AA36: R | AB36: R | AC36: Joan Adon | AD36: Adon, Joan | AE36: 16030 | AF36: Joan Adon | AH36: Joan Adon | AI36: 25629 | AJ36: 6434 | AK36: Joan Adon | AL36: *04ywo* | AM36: Joan Adon | AN36: Joan Adon | AO36: RP | AP36: Adon, Joan | AQ36: Y | AR36: 2e59e623-30ba-4ae9-a63c-3956881a49f2 | AS36: 672851
A37: adriaeh01 | B37: Ehire Adrianza | C37: 32741 | D37: Ehire | E37: Adrianza | F37: LAA | G37: AL | H37: 3B | I37: 8418 | J37: Ehire Adrianza | K37: 501303 | L37: Ehire Adrianza | M37: 1666190 | N37: Ehire Adrianza | O37: adrie001 | P37: adriaeh01 | Q37: 8606 | R37: Ehire Adrianza | S37: 30471 | T37: Ehire Adrianza | V37: ADRIANZA19890821A | W37: 50677 | X37: 9521 | Y37: Ehire Adrianza | Z37: Adrianza, Ehire | AA37: B | AB37: R | AC37: Ehire Adrianza | AD37: Adrianza, Ehire | AE37: 10790 | AH37: Ehire Adrianza | AI37: 8445 | AJ37: 4466 | AK37: Ehire Adrianza | AL37: *01t3l* | AM37: Ehire Adrianza | AN37: Ehire Adrianza | AO37: 3B | AP37: Adrianza, Ehire | AQ37: N | AR37: 15261c81-80fe-4208-84ff-61bf96647609 | AS37: 8418
A38: affelje01 | B38: Jeremy Affeldt | C38: 29012 | D38: Jeremy | E38: Affeldt | F38: N/A | G38: N/A | H38: P | I38: 583 | J38: Jeremy Affeldt | K38: 346793 | L38: Jeremy Affeldt | M38: 223741 | N38: Jeremy Affeldt | O38: affej001 | P38: affelje01 | R38: Jeremy Affeldt | S38: 5061 | T38: Jeremy Affeldt | V38: AFFELDT19790606A | W38: 1354 | X38: 6883 | Y38: Jeremy Affeldt | Z38: Affeldt, Jeremy | AA38: L | AB38: L | AC38: Jeremy Affeldt | AD38: Affeldt, Jeremy | AE38: 6588 | AF38: Jeremy Affeldt | AG38: 5108 | AI38: 14848 | AK38: Jeremy Affeldt | AM38: Jeremy Affeldt | AN38: Jeremy Affeldt | AO38: P | AP38: Affeldt, Jeremy | AQ38: N
A39: agnosza01 | B39: Zach Agnos | C39: 36753 | D39: Zach | E39: Agnos | F39: COL | G39: NL | H39: P | I39: 31552 | J39: Zach Agnos | K39: 688642 | L39: Zach Agnos | N39: Zach Agnos | O39: agnoz001 | P39: agnosza01 | Q39: 12221 | R39: Zach Agnos | T39: Zach Agnos | V39: AGNOS20000815A | Y39: Zach Agnos | Z39: Zach Agnos | AA39: R | AB39: R | AC39: Zach Agnos | AD39: Agnos, Zach | AE39: 19812 | AF39: Zach Agnos | AH39: Zach Agnos | AJ39: 8228 | AK39: Zach Agnos | AL39: *064ny* | AM39: Zach Agnos | AN39: Zach Agnos | AO39: P | AP39: Agnos, Zach | AQ39: Y | AR39: 1a4545a9-b6de-4c0b-b2e5-2714c03f9924 | AS39: 688642
A40: agrazda01 | B40: Dario Agrazal | C40: 34696 | D40: Dario | E40: Agrazal | F40: DET | G40: AL | H40: P | I40: 15821 | J40: Dario Agrazal | K40: 642607 | L40: Dario Agrazal | M40: 2898220 | N40: Dario Agrazal | O40: agrad001 | P40: agrazda01 | Q40: 9849 | R40: Dario Agrazal | S40: 39813 | T40: Dario Agrazal | V40: AGRAZAL19941228A | W40: 103111 | X40: 11185 | Y40: Dario Agrazal | Z40: Agrazal, Dario | AA40: R | AB40: R | AC40: Dario Agrazal | AD40: Agrazal, Dario | AE40: 15247 | AJ40: 6169 | AK40: Dario Agrazal | AL40: *03z9y* | AM40: Dario Agrazal | AN40: Dario Agrazal | AO40: P | AP40: Agrazal, Dario | AQ40: N
A41: aguilje01 | B41: Jesus Aguilar | C41: 33054 | D41: Jesus | E41: Aguilar | F41: ATH | G41: AL | H41: 1B | I41: 11342 | J41: Jesus Aguilar | K41: 542583 | L41: Jesus Aguilar | M41: 1947830 | N41: Jesus Aguilar | O41: aguij001 | P41: aguilje01 | Q41: 8787 | R41: Jesus Aguilar | S41: 32132 | T41: Jesus Aguilar | V41: AGUILAR19900630A | W41: 59871 | X41: 9704 | Y41: Jesús Aguilar | Z41: Aguilar, Jesus | AA41: R | AB41: R | AC41: Jesus Aguilar | AD41: Aguilar, Jesus | AE41: 12327 | AF41: Jesus Aguilar | AG41: 38016 | AH41: Jesus Aguilar | AI41: 9974 | AJ41: 4631 | AK41: Jesus Aguilar | AL41: *02jhn* | AM41: Jesus Aguilar | AN41: Jesus Aguilar | AO41: 1B | AP41: Aguilar, Jesus | AQ41: N | AR41: 144a57ce-80ee-41fc-9831-d664b6564a13 | AS41: 11342
A42: ahmedni01 | B42: Nick Ahmed | C42: 32947 | D42: Nick | E42: Ahmed | F42: TEX | G42: AL | H42: SS | I42: 12147 | J42: Nick Ahmed | K42: 605113 | L42: Nick Ahmed | M42: 1959715 | N42: Nick Ahmed | O42: ahmen001 | P42: ahmedni01 | Q42: 8833 | R42: Nick Ahmed | S42: 32355 | T42: Nick Ahmed | V42: AHMED19900315A | W42: 69508 | X42: 9751 | Y42: Nick Ahmed | Z42: Ahmed, Nick | AA42: R | AB42: R | AC42: Nick Ahmed | AD42: Ahmed, Nick | AE42: 12216 | AF42: Nick Ahmed | AG42: 21612 | AH42: Nick Ahmed | AI42: 18352 | AJ42: 4674 | AK42: Nick Ahmed | AL42: *02br3* | AM42: Nick Ahmed | AN42: Nick Ahmed | AO42: SS | AP42: Ahmed, Nick | AQ42: Y | AR42: 765699df-3282-41b0-9f97-e32a79cc6405 | AS42: 12147
A43: aikenbr01 | B43: Brady Aiken | C43: 35293 | D43: Brady | E43: Aiken | F43: CLE | G43: AL | H43: P | J43: Brady Aiken | K43: 656184 | L43: Brady Aiken | M43: 2135241 | N43: Brady Aiken | P43: aikenbr01 | R43: Brady Aiken | S43: 34953 | T43: Brady Aiken | V43: AIKEN19960816A | W43: 103732 | X43: 10458 | Y43: Brady Aiken | Z43: Aiken, Brady | AA43: L | AB43: L | AC43: Brady Aiken | AD43: Aiken, Brady | AE43: 13357 | AK43: Brady Aiken | AL43: *03b0p* | AM43: Brady Aiken | AN43: Brady Aiken | AO43: P | AP43: Aiken, Brady | AQ43: N
A44: akinke01 | B44: Keegan Akin | C44: 34790 | D44: Keegan | E44: Akin | F44: BAL | G44: AL | H44: P | I44: 19362 | J44: Keegan Akin | K44: 669211 | L44: Keegan Akin | M44: 2449983 | N44: Keegan Akin | O44: akink001 | P44: akinke01 | Q44: 10524 | R44: Keegan Akin | S44: 36724 | T44: Keegan Akin | V44: AKIN19950401A | W44: 108818 | X44: 10431 | Y44: Keegan Akin | Z44: Akin, Keegan | AA44: L | AB44: L | AC44: Keegan Akin | AD44: Akin, Keegan | AE44: 14349 | AI44: 31714 | AJ44: 6520 | AK44: Keegan Akin | AL44: *041py* | AM44: Keegan Akin | AN44: Keegan Akin | AO44: RP | AP44: Akin, Keegan | AQ44: Y | AR44: 22ca7bc6-2dcb-42cd-8060-41ace4bc8e05 | AS44: 669211
A45: akiyash01 | B45: Shogo Akiyama | C45: 32249 | D45: Shogo | E45: Akiyama | F45: N/A | G45: N/A | H45: OF | I45: 27461 | J45: Shogo Akiyama | K45: 673451 | L45: Shogo Akiyama | M45: 3156682 | N45: Shogo Akiyama | O45: akiys001 | P45: akiyash01 | Q45: 10710 | R45: Shogo Akiyama | S45: 42390 | T45: Shogo Akiyama | V45: AKIYAMA19880416A | W45: 111605 | X45: 11721 | Y45: Shogo Akiyama | Z45: Akiyama, Shogo | AA45: L | AB45: R | AC45: Shogo Akiyama | AD45: Akiyama, Shogo | AE45: 14160 | AI45: 38108 | AJ45: 6350 | AK45: Shogo Akiyama | AL45: *058lu* | AM45: Shogo Akiyama | AN45: Shogo Akiyama | AO45: OF | AP45: Akiyama, Shogo | AQ45: N | AR45: 78195909-8ec1-4d2a-b0e1-4d43a13babae
A46: alberan01 | B46: Andrew Albers | C46: 31326 | D46: Andrew | E46: Albers | F46: N/A | G46: N/A | H46: P | I46: 7853 | J46: Andrew Albers | K46: 452027 | L46: Andrew Albers | M46: 2044380 | N46: Andrew Albers | O46: albea001 | P46: alberan01 | Q46: 8567 | R46: Andrew Albers | S46: 32754 | T46: Andrew Albers | V46: ALBERS19851006A | W46: 52617 | X46: 9480 | Y46: Andrew Albers | Z46: Albers, Andrew | AA46: R | AB46: L | AC46: Andrew Albers | AD46: Albers, Andrew | AE46: 12895 | AF46: Andrew Albers | AG46: 38214 | AI46: 17594 | AJ46: 4429 | AK46: Andrew Albers | AL46: *02hts* | AM46: Andrew Albers | AN46: Andrew Albers | AO46: P | AP46: Albers, Andrew | AQ46: N
A47: alberha01 | B47: Hanser Alberto | C47: 33894 | D47: Hanser | E47: Alberto | F47: CHW | G47: AL | H47: 3B | I47: 11902 | J47: Hanser Alberto | K47: 593643 | L47: Hanser Alberto | M47: 2044664 | N47: Hanser Alberto | O47: albeh001 | P47: alberha01 | Q47: 9052 | R47: Hanser Alberto | S47: 32839 | T47: Hanser Alberto | U47: Hanser Alberto | V47: ALBERTO19921017A | W47: 67418 | X47: 9975 | Y47: Hanser Alberto | Z47: Alberto, Hanser | AA47: R | AB47: R | AC47: Hanser Alberto | AD47: Alberto, Hanser | AE47: 12437 | AF47: Hanser Alberto | AH47: Hanser Alberto | AI47: 13277 | AJ47: 4933 | AK47: Hanser Alberto | AL47: *02jtl* | AM47: Hanser Alberto | AN47: Hanser Alberto | AO47: 3B | AP47: Alberto, Hanser | AQ47: N | AS47: 11902
A48: alberma01 | B48: Matt Albers | C48: 30336 | D48: Matt | E48: Albers | F48: MIL | G48: NL | H48: P | I48: 4300 | J48: Matt Albers | K48: 458006 | L48: Matt Albers | M48: 580567 | N48: Matt Albers | O48: albem001 | P48: alberma01 | Q48: 5678 | R48: Matt Albers | S48: 28525 | T48: Matt Albers | V48: ALBERS19830120A | W48: 31948 | X48: 7820 | Y48: Matt Albers | Z48: Albers, Matt | AA48: L | AB48: R | AC48: Matt Albers | AD48: Albers, Matt | AE48: 8027 | AF48: Matt Albers | AG48: 5587 | AH48: Matt Albers | AI48: 513 | AJ48: 2373 | AK48: Matt Albers | AL48: *000hg* | AM48: Matt Albers | AN48: Matt Albers | AO48: P | AP48: Albers, Matt | AQ48: N
A49: albieoz01 | B49: Ozzie Albies | C49: 35437 | D49: Ozzie | E49: Albies | F49: ATL | G49: NL | H49: 2B | I49: 16556 | J49: Ozzie Albies | K49: 645277 | L49: Ozzie Albies | M49: 2167464 | N49: Ozzie Albies | O49: albio001 | P49: albieoz01 | Q49: 9721 | R49: Ozzie Albies | S49: 33783 | T49: Ozzie Albies | V49: ALBIES19970107A | W49: 104004 | X49: 10237 | Y49: Ozzie Albies | Z49: Albies, Ozzie | AA49: B | AB49: R | AC49: Ozzie Albies | AD49: Albies, Ozzie | AE49: 13639 | AH49: Ozzie Albies | AI49: 18397 | AJ49: 5173 | AK49: Ozzie Albies | AL49: *03fi0* | AM49: Ozzie Albies | AN49: Ozzie Albies | AO49: 2B | AP49: Albies, Ozzie | AQ49: Y | AR49: 6853d08e-a028-4e8a-bfb0-bc30e2e0036e | AS49: 16556
A50: albural01 | B50: Al Alburquerque | C50: 31573 | D50: Al | E50: Alburquerque | F50: N/A | G50: N/A | H50: P | I50: 6324 | J50: Al Alburquerque | K50: 456379 | L50: Al Alburquerque | M50: 1725468 | N50: Al Alburquerque | O50: albua001 | P50: albural01 | Q50: 7989 | R50: Al Alburquerque | S50: 30494 | T50: Al Alburquerque | V50: ALBURQUER19860610A | W50: 52489 | X50: 8843 | Y50: Al Alburquerque | Z50: Alburquerque, Al | AA50: R | AB50: R | AC50: Al Alburquerque | AD50: Alburquerque, Al | AE50: 11308 | AF50: Alberto Alburquerque | AG50: 12859 | AH50: Al Alburquerque | AI50: 2839 | AJ50: 3778 | AK50: Al Alburquerque | AL50: *01uuu* | AM50: Al Alburquerque | AN50: Al Alburquerque | AO50: P | AP50: Alburquerque, Al | AQ50: N
A51: alcaljo01 | B51: Jorge Alcala | C51: 34908 | D51: Jorge | E51: Alcala | F51: BOS | G51: AL | H51: P | I51: 19459 | J51: Jorge Alcala | K51: 660896 | L51: Jorge Alcala | M51: 2821135 | N51: Jorge Alcala | O51: alcaj001 | P51: alcaljo01 | Q51: 10701 | R51: Jorge Alcala | S51: 41031 | T51: Jorge Alcala | V51: ALCALA19950728A | W51: 105466 | X51: 11344 | Y51: Jorge Alcala | Z51: Alcala, Jorge | AA51: R | AB51: R | AC51: Jorge Alcala | AD51: Alcala, Jorge | AE51: 14483 | AI51: 22538 | AJ51: 6279 | AK51: Jorge Alcala | AL51: *04ata* | AM51: Jorge Alcala | AN51: Jorge Alcala | AO51: RP | AP51: Alcala, Jorge | AQ51: Y | AR51: f4cee4a2-ba89-4f60-a7b6-21713b58c4a5 | AS51: 660896
A52: alcanar01 | B52: Arismendy Alcantara | C52: 33540 | D52: Arismendy | E52: Alcantara | F52: CIN | G52: NL | H52: OF | I52: 10711 | J52: Arismendy Alcantara | K52: 570489 | L52: Arismendy Alcantara | M52: 2044523 | N52: Arismendy Alcantara | O52: alcaa001 | P52: alcanar01 | Q52: 8640 | R52: Arismendy Alcantara | S52: 32823 | T52: Arismendy Alcantara | V52: ALCANTARA19911029A | W52: 66268 | X52: 9554 | Y52: Arismendy Alcantara | Z52: Alcantara, Arismendy | AA52: B | AB52: R | AC52: Arismendy Alcantara | AD52: Alcantara, Arismendy | AE52: 12841 | AF52: Arismendy Alcantara | AG52: 38602 | AH52: Arismendy Alcantara | AI52: 10541 | AJ52: 4523 | AK52: Arismendy Alcantara | AL52: *02jxv* | AM52: Arismendy Alcantara | AN52: Arismendy Alcantara | AO52: OF | AP52: Alcantara, Arismendy | AQ52: N
A53: alcanke01 | B53: Kevin Alcantara | C53: 37449 | D53: Kevin | E53: Alcantara | F53: CHC | G53: NL | H53: OF | I53: 25971 | J53: Kevin Alcantara | K53: 682634 | L53: Kevin Alcantara | M53: 26913029 | N53: Kevin Alcantara | O53: alcak001 | P53: alcanke01 | Q53: 10406 | R53: Kevin Alcantara | S53: 42500 | T53: Kevin Alcantara | V53: ALCANTARA20020712A | W53: 111669 | X53: 11802 | Y53: Kevin Alcantara | Z53: Alcantara, Kevin | AA53: R | AB53: R | AC53: Kevin Alcantara | AD53: Alcantara, Kevin | AE53: 15607 | AH53: Kevin Alcantara | AI53: 33677 | AJ53: 7914 | AK53: Kevin Alcantara | AL53: *04qow* | AM53: Kevin Alcantara | AN53: Kevin Alcantara | AO53: OF | AP53: Alcantara, Kevin | AQ53: Y | AR53: bdbf2acf-1cf7-48ec-9823-88f2a1c5587a | AS53: 682634
A54: alcansa01 | B54: Sandy Alcantara | C54: 34949 | D54: Sandy | E54: Alcantara | F54: MIA | G54: NL | H54: P | I54: 18684 | J54: Sandy Alcantara | K54: 645261 | L54: Sandy Alcantara | M54: 2211794 | N54: Sandy Alcantara | O54: alcas001 | P54: alcansa01 | Q54: 9754 | R54: Sandy Alcantara | S54: 35241 | T54: Sandy Alcantara | V54: ALCANTARA19950907A | W54: 104002 | X54: 10597 | Y54: Sandy Alcantara | Z54: Alcantara, Sandy | AA54: R | AB54: R | AC54: Sandy Alcantara | AD54: Alcantara, Sandy | AE54: 14071 | AH54: Sandy Alcantara | AI54: 20732 | AJ54: 5698 | AK54: Sandy Alcantara | AL54: *03btv* | AM54: Sandy Alcantara | AN54: Sandy Alcantara | AO54: P | AP54: Alcantara, Sandy | AQ54: Y | AR54: 13a1fc14-ab97-49ea-b197-964b0cbdd20b | AS54: 645261
A55: alcanse01 | B55: Sergio Alcantara | C55: 35256 | D55: Sergio | E55: Alcantara | F55: ARI | G55: NL | H55: SS | I55: 16417 | J55: Sergio Alcantara | K55: 642727 | L55: Sergio Alcantara | M55: 2118128 | N55: Sergio Alcantara | O55: alcas002 | P55: alcanse01 | Q55: 9889 | R55: Sergio Alcantara | S55: 33283 | T55: Sergio Alcantara | V55: ALCANTARA19960710A | W55: 103221 | X55: 11179 | Y55: Sergio Alcantara | Z55: Alcantara, Sergio | AA55: B | AB55: R | AC55: Sergio Alcantara | AD55: Alcantara, Sergio | AE55: 14648 | AI55: 19987 | AJ55: 6317 | AK55: Sergio Alcantara | AL55: *02yh9* | AM55: Sergio Alcantara | AN55: Sergio Alcantara | AO55: SS | AP55: Alcantara, Sergio | AQ55: Y | AR55: f6f18934-b4fc-4330-b4ea-7cc7b213dc00 | AS55: 642727
A56: alcanvi01 | B56: Victor Alcantara | C56: 34062 | D56: Victor | E56: Alcantara | F56: DET | G56: AL | H56: P | I56: 15028 | J56: Victor Alcantara | K56: 622505 | L56: Victor Alcantara | M56: 2167469 | N56: Victor Alcantara | O56: alcav001 | P56: alcanvi01 | Q56: 9231 | R56: Victor Alcantara | S56: 33784 | T56: Victor Alcantara | V56: ALCANTARA19930403A | W56: 100959 | X56: 10187 | Y56: Victor Alcantara | Z56: Alcantara, Victor | AA56: R | AB56: R | AC56: Victor Alcantara | AD56: Alcantara, Victor | AE56: 13726 | AJ56: 5718 | AK56: Victor Alcantara | AL56: *02yo6* | AM56: Victor Alcantara | AN56: Victor Alcantara | AO56: P | AP56: Alcantara, Victor | AQ56: N
A57: alderke01 | B57: Kemp Alderman | C57: 37488 | D57: Kemp | E57: Alderman | F57: MIA | G57: NL | H57: OF | J57: Kemp Alderman | K57: 694580 | L57: Kemp Alderman | N57: Kemp Alderman | P57: alderke01 | Q57: 12518 | R57: Kemp Alderman | T57: Kemp Alderman | V57: ALDERMAN20020820A | Y57: Kemp Alderman | Z57: Alderman, Kemp | AA57: R | AB57: R | AC57: Kemp Alderman | AD57: Alderman, Kemp | AF57: Kemp Alderman | AH57: Kemp Alderman | AK57: Kemp Alderman | AL57: *06ahe* | AM57: Kemp Alderman | AN57: Kemp Alderman | AO57: OF | AP57: Alderman, Kemp | AQ57: Y | AS57: 694580
A58: alexabl01 | B58: Blaze Alexander | C58: 36322 | D58: Blaze | E58: Alexander | F58: BAL | G58: AL | H58: SS | I58: 23789 | J58: Blaze Alexander | K58: 677942 | L58: Blaze Alexander | M58: 2932590 | N58: Blaze Alexander | O58: alexb001 | P58: alexabl01 | Q58: 10142 | R58: Blaze Alexander | S58: 41345 | T58: Blaze Alexander | V58: ALEXANDER19990611A | W58: 111707 | X58: 11415 | Y58: Blaze Alexander | AA58: R | AB58: R | AC58: Blaze Alexander | AD58: Alexander, Blaze | AE58: 15566 | AI58: 35300 | AJ58: 7883 | AK58: Blaze Alexander | AL58: *04pvs* | AM58: Blaze Alexander | AN58: Blaze Alexander | AO58: SS | AP58: Alexander, Blaze | AQ58: Y | AR58: b459c424-409b-4a2f-9808-8a53e5934826 | AS58: 677942
A59: alexaja01 | B59: Jason Alexander | C59: 34029 | D59: Jason | E59: Alexander | F59: ATH | G59: AL | H59: P | I59: 19666 | J59: Jason Alexander | K59: 669920 | L59: Jason Alexander | M59: 2846092 | N59: Jason Alexander | O59: alexj001 | P59: alexaja01 | Q59: 10574 | R59: Jason Alexander | S59: 41849 | T59: Jason Alexander | V59: ALEXANDER19930301A | W59: 109313 | X59: 12628 | Y59: Jason Alexander | Z59: Alexander, Jason | AA59: R | AB59: R | AC59: Jason Alexander | AD59: Alexander, Jason | AE59: 17812 | AF59: Jason Alexander | AH59: Jason Alexander | AI59: 26373 | AJ59: 7023 | AK59: Jason Alexander | AL59: *05xze* | AM59: Jason Alexander | AN59: Jason Alexander | AO59: P | AP59: Alexander, Jason | AQ59: Y | AR59: 49a2e254-5ca0-47a1-9151-89285fab8332 | AS59: 669920
A60: alexasc02 | B60: Scott Alexander | C60: 32699 | D60: Scott | E60: Alexander | F60: ATH | G60: AL | H60: P | I60: 10591 | J60: Scott Alexander | K60: 518397 | L60: Scott Alexander | M60: 2113509 | N60: Scott Alexander | O60: alexs001 | P60: alexasc02 | Q60: 9149 | R60: Scott Alexander | S60: 33123 | T60: Scott Alexander | V60: ALEXANDER19890710A | W60: 65851 | X60: 10072 | Y60: Scott Alexander | Z60: Alexander, Scott | AA60: L | AB60: L | AC60: Scott Alexander | AD60: Alexander, Scott | AE60: 11684 | AH60: Scott Alexander | AI60: 14022 | AJ60: 5023 | AK60: Scott Alexander | AL60: *02hi5* | AM60: Scott Alexander | AN60: Scott Alexander | AO60: RP | AP60: Alexander, Scott | AQ60: Y | AR60: a30a4fbd-3db0-4bc8-9ffb-ac90c9709759 | AS60: 10591
A61: alexaty01 | B61: Tyler Alexander | C61: 34529 | D61: Tyler | E61: Alexander | F61: TB | G61: AL | H61: P | I61: 17735 | J61: Tyler Alexander | K61: 641302 | L61: Tyler Alexander | M61: 2211219 | N61: Tyler Alexander | O61: alext001 | P61: alexaty01 | Q61: 10646 | R61: Tyler Alexander | S61: 40360 | T61: Tyler Alexander | V61: ALEXANDER19940714A | W61: 102160 | X61: 10469 | Y61: Tyler Alexander | Z61: Alexander, Tyler | AA61: R | AB61: L | AC61: Tyler Alexander | AD61: Alexander, Tyler | AE61: 13880 | AI61: 19575 | AJ61: 6075 | AK61: Tyler Alexander | AL61: *0376h* | AM61: Tyler Alexander | AN61: Tyler Alexander | AO61: RP | AP61: Alexander, Tyler | AQ61: Y | AR61: 18d1db5e-d63a-444d-a1ed-ddfc262b8da4 | AS61: 641302
A62: alexyaj01 | B62: A.J. Alexy | C62: 35906 | D62: A.J. | E62: Alexy | F62: CHW | G62: AL | H62: P | I62: 22343 | J62: A.J. Alexy | K62: 669935 | L62: A.J. Alexy | M62: 3077703 | N62: A.J. Alexy | O62: alexa001 | P62: alexyaj01 | Q62: 11175 | R62: A.J. Alexy | S62: 39717 | T62: A.J. Alexy | V62: ALEXY19980421A | W62: 108820 | X62: 11549 | Y62: A.J. Alexy | Z62: Alexy, A.J. | AA62: R | AB62: R | AC62: A.J. Alexy | AD62: Alexy, A.J. | AE62: 14898 | AI62: 33198 | AJ62: 6775 | AK62: A.J. Alexy | AL62: *0429o* | AM62: A.J. Alexy | AN62: A.J. Alexy | AO62: P | AP62: Alexy, A.J. | AQ62: Y | AR62: 085dda92-28e1-4743-9fda-0e1a17c14ef4 | AS62: 669935
A63: alfarjo01 | B63: Jorge Alfaro | C63: 34131 | D63: Jorge | E63: Alfaro | F63: KC | G63: AL | H63: DH | I63: 12180 | J63: Jorge Alfaro | K63: 595751 | L63: Jorge Alfaro | M63: 1846227 | N63: Jorge Alfaro | O63: alfaj002 | P63: alfarjo01 | Q63: 8715 | R63: Jorge Alfaro | S63: 31737 | T63: Jorge Alfaro | V63: ALFARO19881122A | W63: 68062 | X63: 9631 | Y63: Jorge Alfaro | Z63: Alfaro, Jorge | AA63: R | AB63: R | AC63: Jorge Alfaro | AD63: Alfaro, Jorge | AE63: 12391 | AH63: Jorge Alfaro | AI63: 13479 | AJ63: 4985 | AK63: Jorge Alfaro | AL63: *025iy* | AM63: Jorge Alfaro | AN63: Jorge Alfaro | AO63: DH | AP63: Alfaro, Jorge | AQ63: Y | AR63: 7b6762a2-58be-4b26-86b1-6a1d6784a9e9 | AS63: 12180
A64: alforan01 | B64: Anthony Alford | C64: 34535 | D64: Anthony | E64: Alford | F64: N/A | G64: N/A | H64: OF | I64: 14329 | J64: Anthony Alford | K64: 546990 | L64: Anthony Alford | M64: 2044547 | N64: Anthony Alford | O64: alfoa002 | P64: alforan01 | Q64: 9509 | R64: Anthony Alford | S64: 32812 | T64: Anthony Alford | V64: ALFORD19940720A | W64: 100152 | X64: 10240 | Y64: Anthony Alford | Z64: Alford, Anthony | AA64: R | AB64: R | AC64: Anthony Alford | AD64: Alford, Anthony | AE64: 12559 | AH64: Anthony Alford | AI64: 18562 | AJ64: 5197 | AK64: Anthony Alford | AL64: *02my8* | AM64: Anthony Alford | AN64: Anthony Alford | AO64: OF | AP64: Alford, Anthony | AQ64: N
A65: allarko01 | B65: Kolby Allard | C65: 35655 | D65: Kolby | E65: Allard | F65: CLE | G65: AL | H65: P | I65: 18694 | J65: Kolby Allard | K65: 663465 | L65: Kolby Allard | M65: 2184450 | N65: Kolby Allard | O65: allak001 | P65: allarko01 | Q65: 9790 | R65: Kolby Allard | S65: 34980 | T65: Kolby Allard | V65: ALLARD19970813A | W65: 107170 | X65: 10422 | Y65: Kolby Allard | Z65: Allard, Kolby | AA65: L | AB65: L | AC65: Kolby Allard | AD65: Allard, Kolby | AE65: 13820 | AH65: Kolby Allard | AI65: 18532 | AJ65: 5591 | AK65: Kolby Allard | AL65: *03nqg* | AM65: Kolby Allard | AN65: Kolby Allard | AO65: P | AP65: Allard, Kolby | AQ65: Y | AR65: 6be546f6-1196-42d2-b3c7-a6bea36b0347 | AS65: 663465
A66: allenau01 | B66: Austin Allen | C66: 34350 | D66: Austin | E66: Allen | F66: ATH | G66: AL | H66: C | I66: 18083 | J66: Austin Allen | K66: 664119 | L66: Austin Allen | M66: 2447462 | N66: Austin Allen | O66: allea001 | P66: allenau01 | Q66: 10138 | R66: Austin Allen | S66: 39870 | T66: Austin Allen | V66: ALLEN19940116A | W66: 105476 | X66: 11229 | Y66: Austin Allen | Z66: Allen, Austin | AA66: L | AB66: R | AC66: Austin Allen | AD66: Allen, Austin | AE66: 13924 | AI66: 22718 | AJ66: 6135 | AK66: Austin Allen | AL66: *03qkr* | AM66: Austin Allen | AN66: Austin Allen | AO66: C | AP66: Allen, Austin | AQ66: Y | AR66: e2cea33b-8f78-416f-9700-4a5746bfbfce
A67: allenco01 | B67: Cody Allen | C67: 32467 | D67: Cody | E67: Allen | F67: TEX | G67: AL | H67: P | I67: 12183 | J67: Cody Allen | K67: 592102 | L67: Cody Allen | M67: 1953416 | N67: Cody Allen | O67: allec002 | P67: allenco01 | Q67: 8346 | R67: Cody Allen | S67: 32188 | T67: Cody Allen | V67: ALLEN19881120A | W67: 68494 | X67: 9243 | Y67: Cody Allen | Z67: Allen, Cody | AA67: R | AB67: R | AC67: Cody Allen | AD67: Allen, Cody | AE67: 12627 | AF67: Cody Allen | AG67: 17054 | AH67: Cody Allen | AI67: 18205 | AJ67: 4153 | AK67: Cody Allen | AL67: *02ho1* | AM67: Cody Allen | AN67: Cody Allen | AO67: P | AP67: Allen, Cody | AQ67: N
A68: allengr01 | B68: Greg Allen | C68: 34043 | D68: Greg | E68: Allen | F68: NYY | G68: AL | H68: OF | I68: 16623 | J68: Greg Allen | K68: 656185 | L68: Greg Allen | M68: 2171381 | N68: Greg Allen | O68: alleg002 | P68: allengr01 | Q68: 9744 | R68: Greg Allen | S68: 34187 | T68: Greg Allen | V68: ALLEN19930315A | W68: 104718 | X68: 10460 | Y68: Greg Allen | Z68: Allen, Greg | AA68: B | AB68: R | AC68: Greg Allen | AD68: Allen, Greg | AE68: 14405 | AH68: Greg Allen | AI68: 20381 | AJ68: 5188 | AK68: Greg Allen | AL68: *03dez* | AM68: Greg Allen | AN68: Greg Allen | AO68: OF | AP68: Allen, Greg | AQ68: Y | AR68: 25f1abc7-8aaf-4b2f-a78f-7220111312c0 | AS68: 16623
A69: allenlo01 | B69: Logan Allen | C69: 35573 | D69: Logan | E69: Allen | F69: ARI | G69: NL | H69: P | I69: 18555 | J69: Logan Allen | K69: 663531 | L69: Logan Allen | M69: 2211756 | N69: Logan Allen | O69: allel002 | P69: allenlo01 | Q69: 10276 | R69: Logan Allen | S69: 35024 | T69: Logan Allen | V69: ALLEN19970523A | W69: 105477 | X69: 10938 | Y69: Logan Allen | Z69: Allen, Logan | AA69: R | AB69: L | AC69: Logan Allen | AD69: Allen, Logan | AE69: 14079 | AH69: Logan Allen | AI69: 22763 | AJ69: 5942 | AK69: Logan Allen | AL69: *03qnb* | AM69: Logan Allen | AN69: Logan Allen | AO69: RP | AP69: Allen, Logan | AQ69: Y | AR69: dc65a6dc-eaae-4765-95a7-a926e737cec2 | AS69: 663531
A70: allenlo02 | B70: Logan Allen | C70: 36043 | D70: Logan | E70: Allen | F70: CLE | G70: AL | H70: P | I70: 27589 | J70: Logan Allen | K70: 671106 | L70: Logan Allen | M70: 26757783 | N70: Logan Taylor Allen | O70: allel003 | P70: allenlo02 | Q70: 11412 | R70: Logan Allen | S70: 4683350 | T70: Logan Allen | V70: ALLEN19980905A | W70: 111773 | X70: 60139 | Y70: Logan Allen | AA70: R | AB70: L | AC70: Logan Allen | AD70: Allen, Logan | AE70: 16715 | AI70: 38349 | AJ70: 6914 | AK70: Logan Allen | AL70: *05jp3* | AM70: Logan Allen | AN70: Logan Allen | AO70: SP | AP70: Allen, Logan | AQ70: Y | AR70: 64f142b5-cdac-4177-a84e-c8a9a364bbb7 | AS70: 671106
A71: allenni02 | B71: Nick Allen | C71: 36076 | D71: Nick | E71: Allen | F71: HOU | G71: AL | H71: SS | I71: 22277 | J71: Nick Allen | K71: 669397 | L71: Nick Allen | M71: 2836533 | N71: Nick Allen | O71: allen002 | P71: allenni02 | Q71: 10857 | R71: Nick Allen | S71: 40338 | T71: Nick Allen | V71: ALLEN19981008A | W71: 109318 | X71: 11359 | Y71: Nick Allen | Z71: Allen, Nick | AA71: R | AB71: R | AC71: Nick Allen | AD71: Allen, Nick | AE71: 14788 | AF71: Nick Allen | AH71: Nick Allen | AI71: 26860 | AJ71: 6328 | AK71: Nick Allen | AL71: *04efs* | AM71: Nick Allen | AN71: Nick Allen | AO71: SS | AP71: Allen, Nick | AQ71: Y | AR71: 2ec32306-8202-403a-975a-09af74c49ab3 | AS71: 669397
A72: almonab01 | B72: Abraham Almonte | C72: 32686 | D72: Abraham | E72: Almonte | F72: NYM | G72: NL | H72: DH | I72: 5486 | J72: Abraham Almonte | K72: 501659 | L72: Abraham Almonte | M72: 1813191 | N72: Abraham Almonte | O72: almoa001 | P72: almonab01 | Q72: 8591 | R72: Abraham Almonte | S72: 31474 | T72: Abraham Almonte | V72: ALMONTE19890627A | W72: 50910 | X72: 9506 | Y72: Abraham Almonte | Z72: Almonte, Abraham | AA72: B | AB72: R | AC72: Abraham Almonte | AD72: Almonte, Abraham | AE72: 12414 | AF72: Abraham Almonte | AG72: 14019 | AH72: Abraham Almonte | AI72: 4422 | AJ72: 4452 | AK72: Abraham Almonte | AL72: *037u4* | AM72: Abraham Almonte | AN72: Abraham Almonte | AO72: DH | AP72: Almonte, Abraham | AQ72: N | AS72: 5486
A73: almonye01 | B73: Yency Almonte | C73: 34489 | D73: Yency | E73: Almonte | F73: CHC | G73: NL | H73: P | I73: 15068 | J73: Yency Almonte | K73: 622075 | L73: Yency Almonte | M73: 2118907 | N73: Yency Almonte | O73: almoy001 | P73: almonye01 | Q73: 9494 | R73: Yency Almonte | S73: 36064 | T73: Yency Almonte | V73: ALMONTE19940604A | W73: 100720 | X73: 10871 | Y73: Yency Almonte | Z73: Almonte, Yency | AA73: B | AB73: R | AC73: Yency Almonte | AD73: Almonte, Yency | AE73: 13722 | AI73: 23782 | AJ73: 5911 | AK73: Yency Almonte | AL73: *02n7z* | AM73: Yency Almonte | AN73: Yency Almonte | AO73: RP | AP73: Almonte, Yency | AQ73: Y | AR73: 06537388-c2f8-465e-87c6-a9462aa8edd6 | AS73: 622075
A74: almonzo01 | B74: Zoilo Almonte | C74: 32669 | D74: Zoilo | E74: Almonte | F74: N/A | G74: N/A | H74: OF | I74: 6732 | J74: Zoilo Almonte | K74: 501660 | L74: Zoilo Almonte | M74: 1812890 | N74: Zoilo Almonte | O74: almoz001 | P74: almonzo01 | R74: Zoilo Almonte | S74: 31469 | T74: Zoilo Almonte | U74: Zoilo Almonte | V74: ALMONTE19890610A | W74: 50911 | X74: 9436 | Y74: Zoilo Almonte | Z74: Almonte, Zoilo | AA74: B | AB74: R | AC74: Zoilo Almonte | AD74: Almonte, Zoilo | AE74: 12338 | AI74: 9387 | AK74: Zoilo Almonte | AL74: *02i2v* | AM74: Zoilo Almonte | AN74: Zoilo Almonte | AO74: OF | AP74: Almonte, Zoilo | AQ74: N
A75: almoral01 | B75: Albert Almora | C75: 34440 | D75: Albert | E75: Almora | F75: MIA | G75: NL | H75: OF | I75: 14109 | J75: Albert Almora Jr. | K75: 546991 | L75: Albert Almora | M75: 2000031 | N75: Albert Almora | O75: almoa002 | P75: almoral01 | Q75: 8639 | R75: Albert Almora Jr. | S75: 32686 | T75: Albert Almora | V75: ALMORA19940416A | W75: 70339 | X75: 9553 | Y75: Albert Almora Jr. | Z75: Almora Jr., Albert | AA75: R | AB75: R | AC75: Albert Almora Jr. | AD75: Almora, Albert | AE75: 12497 | AF75: Albert Almora Jr. | AG75: 38276 | AH75: Albert Almora Jr. | AI75: 18186 | AJ75: 4801 | AK75: Albert Almora Jr. | AL75: *02i2o* | AM75: Albert Almora Jr. | AN75: Albert Almora Jr. | AO75: OF | AP75: Almora Jr., Albert | AQ75: Y | AS75: 14109
A76: alonspe01 | B76: Pete Alonso | C76: 34675 | D76: Pete | E76: Alonso | F76: BAL | G76: AL | H76: 1B | I76: 19251 | J76: Pete Alonso | K76: 624413 | L76: Pete Alonso | M76: 2447476 | N76: Pete Alonso | O76: alonp001 | P76: alonspe01 | Q76: 10312 | R76: Pete Alonso | S76: 37498 | T76: Pete Alonso | V76: ALONSO19941207A | W76: 101603 | X76: 10918 | Y76: Pete Alonso | Z76: Alonso, Pete | AA76: R | AB76: R | AC76: Pete Alonso | AD76: Alonso, Pete | AE76: 14300 | AI76: 23859 | AJ76: 5829 | AK76: Pete Alonso | AL76: *041pz* | AM76: Pete Alonso | AN76: Pete Alonso | AO76: 1B | AP76: Alonso, Pete | AQ76: Y | AR76: 37ab6c32-3cc0-4297-8c26-652590267dbc | AS76: 624413
A77: alonsyo01 | B77: Yonder Alonso | C77: 31875 | D77: Yonder | E77: Alonso | F77: COL | G77: NL | H77: 1B | I77: 2530 | J77: Yonder Alonso | K77: 475174 | L77: Yonder Alonso | M77: 1629156 | N77: Yonder Alonso | O77: alony001 | P77: alonsyo01 | Q77: 7563 | R77: Yonder Alonso | S77: 30016 | T77: Yonder Alonso | U77: Yonder Alonso | V77: ALONSO19870408A | W77: 58012 | X77: 8660 | Y77: Yonder Alonso | Z77: Alonso, Yonder | AA77: L | AB77: R | AC77: Yonder Alonso | AD77: Alonso, Yonder | AE77: 10467 | AF77: Yonder Alonso | AG77: 12521 | AH77: Yonder Alonso | AI77: 5165 | AJ77: 3390 | AK77: Yonder Alonso | AL77: *01c51* | AM77: Yonder Alonso | AN77: Yonder Alonso | AO77: 1B | AP77: Alonso, Yonder | AQ77: N
A78: altavda01 | B78: Dan Altavilla | C78: 33855 | D78: Dan | E78: Altavilla | F78: CHW | G78: AL | H78: P | I78: 16507 | J78: Dan Altavilla | K78: 656186 | L78: Dan Altavilla | M78: 2169865 | N78: Dan Altavilla | O78: altad001 | P78: altavda01 | Q78: 9440 | R78: Dan Altavilla | S78: 35222 | T78: Dan Altavilla | V78: ALTAVILLA19920908A | W78: 104719 | X78: 10378 | Y78: Dan Altavilla | Z78: Altavilla, Dan | AA78: R | AB78: R | AC78: Dan Altavilla | AD78: Altavilla, Dan | AE78: 14530 | AF78: Dan Altavilla | AG78: 73828 | AH78: Dan Altavilla | AI78: 20455 | AJ78: 5366 | AK78: Dan Altavilla | AL78: *03dec* | AM78: Dan Altavilla | AN78: Dan Altavilla | AO78: P | AP78: Altavilla, Dan | AQ78: Y | AR78: 943cebc7-2933-41ed-90ec-7fba862aecd0 | AS78: 16507
A79: altheaa01 | B79: Aaron Altherr | C79: 33252 | D79: Aaron | E79: Altherr | F79: NYM | G79: NL | H79: OF | I79: 11270 | J79: Aaron Altherr | K79: 571437 | L79: Aaron Altherr | M79: 2107840 | N79: Aaron Altherr | O79: altha001 | P79: altheaa01 | Q79: 8814 | R79: Aaron Altherr | S79: 31738 | T79: Aaron Altherr | V79: ALTHERR19910114A | W79: 59584 | X79: 9734 | Y79: Aaron Altherr | Z79: Altherr, Aaron | AA79: R | AB79: R | AC79: Aaron Altherr | AD79: Altherr, Aaron | AE79: 11376 | AF79: Aaron Altherr | AG79: 54952 | AH79: Aaron Altherr | AI79: 12359 | AJ79: 4653 | AK79: Aaron Altherr | AL79: *02484* | AM79: Aaron Altherr | AN79: Aaron Altherr | AO79: OF | AP79: Altherr, Aaron | AQ79: N
A80: altuvjo01 | B80: Jose Altuve | C80: 32999 | D80: Jose | E80: Altuve | F80: HOU | G80: AL | H80: 2B | I80: 5417 | J80: Jose Altuve | K80: 514888 | L80: Jose Altuve | M80: 1839905 | N80: Jose Altuve | O80: altuj001 | P80: altuvjo01 | Q80: 8116 | R80: Jose Altuve | S80: 31662 | T80: Jose Altuve | U80: Jose Altuve | V80: ALTUVE19900506A | W80: 55877 | X80: 8996 | Y80: Jose Altuve | Z80: Altuve, Jose | AA80: R | AB80: R | AC80: Jose Altuve | AD80: Altuve, Jose | AE80: 12118 | AF80: Jose Altuve | AG80: 14562 | AH80: Jose Altuve | AI80: 5918 | AJ80: 3863 | AK80: Jose Altuve | AL80: *024m0* | AM80: Jose Altuve | AN80: Jose Altuve | AO80: 2B | AP80: Altuve, Jose | AQ80: Y | AR80: fa20fddf-1607-4df3-9b02-6e5807fb4a99 | AS80: 5417
A81: aluja01 | B81: Jake Alu | C81: 35526 | D81: Jake | E81: Alu | F81: WAS | G81: NL | H81: 2B | I81: 25569 | J81: Jake Alu | K81: 666906 | L81: Jake Alu | M81: 28841679 | N81: Jake Alu | O81: alu-j001 | P81: aluja01 | Q81: 11660 | R81: Jake Alu | S81: 5010414 | T81: Jacob Alu | V81: ALU19970406A | W81: 111855 | AA81: L | AB81: R | AC81: Jake Alu | AD81: Alu, Jake | AE81: 18110 | AI81: 36835 | AJ81: 7265 | AK81: Jake Alu | AL81: *051io* | AM81: Jake Alu | AN81: Jake Alu | AO81: 2B | AP81: Alu, Jake | AQ81: N | AS81: 666906
A82: alvaran01 | B82: Andrew Alvarez | C82: 36324 | D82: Andrew | E82: Alvarez | F82: WAS | G82: NL | H82: P | I82: 29914 | J82: Andrew Alvarez | K82: 674841 | L82: Andrew Alvarez | N82: Andrew Alvarez | O82: alvaa003 | P82: alvaran01 | Q82: 12454 | R82: Andrew Alvarez | T82: Andrew Alvarez | V82: ALVAREZ19990613A | Y82: Andrew Alvarez | Z82: Andrew Alvarez | AA82: R | AB82: R | AC82: Andrew Alvarez | AD82: Alvarez, Andrew | AE82: 19439 | AF82: Andrew Alvarez | AH82: Andrew Alvarez | AJ82: 8397 | AK82: Andrew Alvarez | AL82: *060u3* | AM82: Andrew Alvarez | AN82: Andrew Alvarez | AO82: P | AP82: Alvarez, Andrew | AQ82: Y | AR82: 213885d5-4ae8-472c-a92a-d0a8b59ff049 | AS82: 674841
A83: alvarar01 | B83: Armando Alvarez | C83: 34529 | D83: Armando | E83: Alvarez | F83: MIN | G83: AL | H83: 3B | I83: 19292 | J83: Armando Alvarez | K83: 669137 | L83: Armando Alvarez | M83: 3157904 | N83: Armando Alvarez | O83: alvaa002 | P83: alvarar01 | Q83: 12064 | R83: Armando Alvarez | T83: Armando Alvarez | V83: ALVAREZ19940714A | W83: 107397 | Y83: Armando Alvarez | Z83: Alvarez, Armando | AA83: R | AB83: R | AC83: Armando Alvarez | AD83: Alvarez, Armando | AE83: 18377 | AJ83: 8026 | AK83: Armando Alvarez | AL83: *0420k* | AM83: Armando Alvarez | AN83: Armando Alvarez | AO83: 3B | AP83: Alvarez, Armando | AQ83: Y | AR83: b31b1b2b-06bd-4c5b-a015-3fd76109d881 | AS83: 669137
A84: alvared01 | B84: Eddy Alvarez | C84: 32903 | D84: Eddy | E84: Alvarez | F84: ATL | G84: NL | H84: 2B | I84: 16959 | J84: Eddy Alvarez | K84: 657193 | L84: Eddy Alvarez | M84: 2734420 | N84: Eddy Alvarez | O84: alvae001 | P84: alvared01 | Q84: 10836 | R84: Eddy Alvarez | S84: 36474 | T84: Eddy Alvarez | V84: ALVAREZ19900130A | W84: 104966 | X84: 11915 | Y84: Eddy Alvarez | Z84: Alvarez, Eddy | AA84: L | AB84: R | AC84: Eddy Alvarez | AD84: Alvarez, Eddy | AE84: 13517 | AF84: Eddy Alvarez | AH84: Eddy Alvarez | AI84: 20232 | AJ84: 6424 | AK84: Eddy Alvarez | AL84: *03mpn* | AM84: Eddy Alvarez | AN84: Eddy Alvarez | AO84: 2B | AP84: Alvarez, Eddy | AQ84: Y | AS84: 657193
A85: alvarel01 | B85: Elvis Alvarado | C85: 36214 | D85: Elvis | E85: Alvarado | F85: ATH | G85: AL | H85: P | I85: 21662 | J85: Elvis Alvarado | K85: 665660 | L85: Elvis Alvarado | N85: Elvis Alvarado | O85: alvae002 | P85: alvarel01 | Q85: 12340 | R85: Elvis Alvarado | T85: Elvis Alvarado | V85: ALVARADO19990223A | Y85: Elvis Alvarado | Z85: Elvis Alvarado | AA85: R | AB85: R | AC85: Elvis Alvarado | AD85: Alvarado, Elvis | AE85: 13995 | AF85: Elvis Alvarado | AH85: Elvis Alvarado | AJ85: 8250 | AK85: Elvis Alvarado | AL85: *041g5* | AM85: Elvis Alvarado | AN85: Elvis Alvarado | AO85: P | AP85: Alvarado, Elvis | AQ85: Y | AR85: e3cd1629-74ed-4a48-b257-a9c6b8964cde | AS85: 665660
A86: alvarfr01 | B86: Francisco Alvarez | C86: 37214 | D86: Francisco | E86: Alvarez | F86: NYM | G86: NL | H86: C | I86: 26121 | J86: Francisco Alvarez | K86: 682626 | L86: Francisco Alvarez | M86: 3152036 | N86: Francisco Alvarez | O86: alvaf001 | P86: alvarfr01 | Q86: 11118 | R86: Francisco Alvarez | S86: 41253 | T86: Francisco Alvarez | V86: ALVAREZ20011119A | W86: 111885 | X86: 11349 | Y86: Francisco Alvarez | Z86: Francisco Alvarez | AA86: R | AB86: R | AC86: Francisco Alvarez | AD86: Alvarez, Francisco | AE86: 15610 | AF86: Francisco Alvarez | AH86: Francisco Alvarez | AI86: 37427 | AJ86: 6563 | AK86: Francisco Alvarez | AL86: *04qnc* | AM86: Francisco Alvarez | AN86: Francisco Alvarez | AO86: C | AP86: Alvarez, Francisco | AQ86: Y | AR86: e2e38417-c304-4250-a11c-cfd69469a1de | AS86: 682626
A87: alvarha01 | B87: Hayden Alvarez | C87: 39160 | D87: Hayden | E87: Alvarez | F87: LAA | G87: AL | H87: OF | J87: Hayden Alvarez | K87: 820986 | L87: Hayden Alvarez | N87: Hayden Alvarez | P87: alvarha01 | R87: Hayden Alvarez | T87: Hayden Alvarez | V87: ALVAREZ20070319A | Y87: Hayden Alvarez | Z87: Hayden Alvarez | AA87: R | AB87: R | AC87: Hayden Alvarez | AD87: Alvarez, Hayden | AF87: Hayden Alvarez | AH87: Hayden Alvarez | AL87: *06jfc* | AM87: Hayden Alvarez | AN87: Hayden Alvarez | AO87: OF | AP87: Alvarez, Hayden | AQ87: Y
A88: alvarhe01 | B88: Henderson Alvarez | C88: 32981 | D88: Henderson | E88: Alvarez | F88: PHI | G88: NL | H88: P | I88: 5669 | J88: Henderson Alvarez | K88: 506693 | L88: Henderson Alvarez | M88: 1756627 | N88: Henderson Alvarez | O88: alvah001 | P88: alvarhe01 | R88: Henderson Alvarez | S88: 31047 | T88: Henderson Alvarez | V88: ALVAREZ19900418A | W88: 55886 | X88: 9011 | Y88: Henderson Alvarez | Z88: Alvarez, Henderson | AA88: R | AB88: R | AC88: Henderson Alvarez | AD88: Alvarez, Henderson | AE88: 11198 | AF88: Henderson Alvarez | AG88: 13061 | AH88: Henderson Alvarez | AI88: 4979 | AJ88: 3884 | AK88: Henderson Alvarez | AL88: *01skb* | AM88: Henderson Alvarez | AN88: Henderson Alvarez | AO88: P | AP88: Alvarez, Henderson | AQ88: N
A89: alvarjo01 | B89: Jose Alvarez | C89: 32634 | D89: Jose | E89: Alvarez | F89: N/A | G89: N/A | H89: P | I89: 5358 | J89: Jose Alvarez | K89: 501625 | L89: Jose Alvarez | M89: 1945280 | N89: Jose Alvarez | O89: alvaj001 | P89: alvarjo01 | Q89: 8519 | R89: Jose Alvarez | S89: 32099 | T89: Jose Alvarez | V89: ALVAREZ19890506A | W89: 50878 | X89: 9429 | Y89: Jose Alvarez | Z89: Alvarez, Jose | AA89: R | AB89: R | AC89: Jose Alvarez | AD89: Alvarez, Jose | AE89: 11284 | AF89: Jose Alvarez | AG89: 38007 | AH89: Jose Alvarez | AI89: 6145 | AJ89: 4390 | AK89: Jose Alvarez | AL89: *021hr* | AM89: Jose Alvarez | AN89: Jose Alvarez | AO89: P | AP89: Alvarez, Jose | AQ89: N
A90: alvarjo03 | B90: Jose Alvarado | C90: 34840 | D90: Jose | E90: Alvarado | F90: PHI | G90: NL | H90: P | I90: 17780 | J90: Jose Alvarado | K90: 621237 | L90: Jose Alvarado | M90: 2444515 | N90: Jose Alvarado | O90: alvaj004 | P90: alvarjo03 | Q90: 9515 | R90: Jose Alvarado | S90: 36063 | T90: Jose Alvarado | V90: ALVARADO19950521A | W90: 100568 | X90: 10692 | Y90: José Alvarado | Z90: Alvarado, Jose | AA90: L | AB90: L | AC90: Jose Alvarado | AD90: Alvarado, Jose | AE90: 14610 | AH90: Jose Alvarado | AI90: 29992 | AJ90: 5547 | AK90: Jose Alvarado | AL90: *03btm* | AM90: Jose Alvarado | AN90: Jose Alvarado | AO90: RP | AP90: Alvarado, Jose | AQ90: Y | AR90: f59606d1-98aa-4c0b-b66a-c095f2f2c84c | AS90: 621237
A91: alvarna01 | B91: Nacho Alvarez | C91: 37722 | D91: Nacho | E91: Alvarez | F91: ATL | G91: NL | H91: 2B | I91: 31765 | J91: Nacho Alvarez Jr. | K91: 805373 | L91: Nacho Alvarez Jr. | M91: 29085442 | N91: Ignacio Alvarez | O91: alvan001 | P91: alvarna01 | Q91: 12129 | R91: Nacho Alvarez Jr. | S91: 5133834 | T91: Nacho Alvarez Jr. | V91: ALVAREZ20030411A | W91: 163722 | X91: 62057 | Y91: Nacho Alvarez Jr. | Z91: Alvarez, Nacho | AA91: R | AB91: R | AC91: Nacho Alvarez Jr. | AD91: Alvarez, Nacho | AE91: 18143 | AI91: 42206 | AJ91: 8043 | AK91: Nacho Alvarez Jr. | AL91: *064da* | AM91: Nacho Alvarez Jr. | AN91: Nacho Alvarez Jr. | AO91: 2B | AP91: Alvarez Jr., Nacho | AQ91: Y | AS91: 805373
A92: alvarpe01 | B92: Pedro Alvarez | C92: 31814 | D92: Pedro | E92: Alvarez | F92: BAL | G92: AL | H92: DH | I92: 2495 | J92: Pedro Alvarez | K92: 476883 | L92: Pedro Alvarez | M92: 1630071 | N92: Pedro Alvarez | O92: alvap001 | P92: alvarpe01 | Q92: 7003 | R92: Pedro Alvarez | S92: 29962 | T92: Pedro Alvarez | U92: Pedro Alvarez | V92: ALVAREZ19870718A | W92: 59218 | X92: 8645 | Y92: Pedro Alvarez | Z92: Alvarez, Pedro | AA92: L | AB92: R | AC92: Pedro Alvarez | AD92: Alvarez, Pedro | AE92: 10199 | AF92: Pedro Alvarez | AG92: 11098 | AH92: Pedro Alvarez | AI92: 5654 | AJ92: 3116 | AK92: Pedro Alvarez | AL92: *01bvn* | AM92: Pedro Alvarez | AN92: Pedro Alvarez | AO92: DH | AP92: Alvarez, Pedro | AQ92: N
A93: alvarya01 | B93: Yadier Alvarez | C93: 35131 | D93: Yadier | E93: Alvarez | F93: LAD | G93: NL | H93: P | J93: Yadier Alvarez | K93: 665751 | L93: Yadier Alvarez | M93: 2227140 | N93: Yadier Alvarez | P93: alvarya01 | Q93: 9826 | R93: Yadier Alvarez | S93: 34960 | T93: Yadier Alvarez | V93: ALVAREZ19960307A | W93: 107180 | X93: 10507 | Y93: Yadier Alvarez | Z93: Alvarez, Yadier | AA93: R | AB93: R | AC93: Yadier Alvarez | AD93: Alvarez, Yadier | AE93: 13734 | AH93: Yadier Alvarez | AJ93: 5740 | AK93: Yadier Alvarez | AL93: *03mod* | AM93: Yadier Alvarez | AN93: Yadier Alvarez | AO93: P | AP93: Alvarez, Yadier | AQ93: N
A94: alvaryo01 | B94: Yordan Alvarez | C94: 35608 | D94: Yordan | E94: Alvarez | F94: HOU | G94: AL | H94: OF | I94: 19556 | J94: Yordan Alvarez | K94: 670541 | L94: Yordan Alvarez | M94: 2507341 | N94: Yordan Alvarez | O94: alvay001 | P94: alvaryo01 | Q94: 10367 | R94: Yordan Alvarez | S94: 36018 | T94: Yordan Alvarez | V94: ALVAREZ19970627A | W94: 109147 | X94: 10883 | Y94: Yordan Alvarez | Z94: Alvarez, Yordan | AA94: L | AB94: R | AC94: Yordan Alvarez | AD94: Alvarez, Yordan | AE94: 14407 | AH94: Yordan Alvarez | AI94: 23795 | AJ94: 5926 | AK94: Yordan Alvarez | AL94: *04355* | AM94: Yordan Alvarez | AN94: Yordan Alvarez | AO94: OF | AP94: Alvarez, Yordan | AQ94: Y | AR94: 3866743c-5a54-4515-8210-fd76d80cca68 | AS94: 670541
A95: alzolad01 | B95: Adbert Alzolay | C95: 34759 | D95: Adbert | E95: Alzolay | F95: NYM | G95: NL | H95: P | I95: 17859 | J95: Adbert Alzolay | K95: 640470 | L95: Adbert Alzolay | M95: 2821213 | N95: Adbert Alzolay | O95: alzoa001 | P95: alzolad01 | Q95: 9886 | R95: Adbert Alzolay | S95: 39802 | T95: Adbert Alzolay | V95: ALZOLAY19950301A | W95: 102443 | X95: 10858 | Y95: Adbert Alzolay | Z95: Alzolay, Adbert | AA95: R | AB95: R | AC95: Adbert Alzolay | AD95: Alzolay, Adbert | AE95: 15098 | AH95: Adbert Alzolay | AI95: 18751 | AJ95: 6177 | AK95: Adbert Alzolay | AL95: *03aqz* | AM95: Adbert Alzolay | AN95: Adbert Alzolay | AO95: RP | AP95: Alzolay, Adbert | AQ95: Y | AR95: d2c4ff67-2927-4f94-891a-dad3f4953f63 | AS95: 640470
A96: amadoad01 | B96: Adael Amador | C96: 37722 | D96: Adael | E96: Amador | F96: COL | G96: NL | H96: SS | I96: 27962 | J96: Adael Amador | K96: 691182 | L96: Adael Amador | M96: 3151953 | N96: Adael Amador | O96: amada001 | P96: amadoad01 | Q96: 11965 | R96: Adael Amador | V96: AMADOR20030411A | W96: 147898 | X96: 12411 | AA96: B | AB96: R | AC96: Adael Amador | AD96: Amador, Adael | AE96: 16329 | AI96: 38448 | AJ96: 8007 | AK96: Adael Amador | AL96: *04ysv* | AM96: Adael Amador | AN96: Adael Amador | AO96: SS | AP96: Amador, Adael | AQ96: Y | AR96: 9464f7d8-b123-4dd7-94a0-6f1751e0515d | AS96: 691182
A97: amarial01 | B97: Alexi Amarista | C97: 32604 | D97: Alexi | E97: Amarista | F97: N/A | G97: N/A | H97: OF | I97: 9063 | J97: Alexi Amarista | K97: 506560 | L97: Alexi Amarista | M97: 1735053 | N97: Alexi Amarista | O97: amara001 | P97: amarial01 | Q97: 8056 | R97: Alexi Amarista | S97: 30562 | T97: Alexi Amarista | U97: Alexi Amarista | V97: AMARISTA19890406A | W97: 55889 | X97: 8914 | Y97: Alexi Amarista | Z97: Amarista, Alexi | AA97: L | AB97: R | AC97: Alexi Amarista | AD97: Amarista, Alexi | AE97: 11377 | AF97: Alexi Amarista | AG97: 13014 | AH97: Alexi Amarista | AI97: 18083 | AJ97: 3785 | AK97: Alexi Amarista | AL97: *01sjn* | AM97: Alexi Amarista | AN97: Alexi Amarista | AO97: OF | AP97: Amarista, Alexi | AQ97: N
A98: amayaja01 | B98: Jacob Amaya | C98: 36041 | D98: Jacob | E98: Amaya | F98: CHW | G98: AL | H98: SS | I98: 23296 | J98: Jacob Amaya | K98: 676070 | L98: Jacob Amaya | M98: 2836540 | N98: Jacob Amaya | O98: amayj001 | P98: amayaja01 | Q98: 10398 | R98: Jacob Amaya | S98: 42106 | T98: Jacob Amaya | V98: AMAYA19980903A | W98: 111090 | X98: 11777 | Y98: Jacob Amaya | AA98: R | AB98: R | AC98: Jacob Amaya | AD98: Amaya, Jacob | AE98: 15571 | AI98: 27057 | AJ98: 7224 | AK98: Jacob Amaya | AL98: *04elh* | AM98: Jacob Amaya | AN98: Jacob Amaya | AO98: SS | AP98: Amaya, Jacob | AQ98: Y | AR98: 4cbdf28f-a260-46fd-9689-c5277c1e7e07 | AS98: 676070
A99: amayami01 | B99: Miguel Amaya | C99: 36228 | D99: Miguel | E99: Amaya | F99: CHC | G99: NL | H99: C | I99: 21693 | J99: Miguel Amaya | K99: 665804 | L99: Miguel Amaya | M99: 2804019 | N99: Miguel Amaya | O99: amaym001 | P99: amayami01 | Q99: 10290 | R99: Miguel Amaya | S99: 38905 | T99: Miguel Amaya | V99: AMAYA19990309A | W99: 107401 | X99: 11075 | Y99: Miguel Amaya | AA99: R | AB99: R | AC99: Miguel Amaya | AD99: Amaya, Miguel | AE99: 13978 | AI99: 32321 | AJ99: 6614 | AK99: Miguel Amaya | AL99: *03xs3* | AM99: Miguel Amaya | AN99: Miguel Amaya | AO99: C | AP99: Amaya, Miguel | AQ99: Y | AR99: e0eb1dfc-ce87-4ff2-a8f4-7d1afd5720b4 | AS99: 665804
A100: ambrihe01 | B100: Hector Ambriz | C100: 30826 | D100: Hector | E100: Ambriz | F100: SD | G100: NL | H100: P | I100: 559 | J100: Hector Ambriz | K100: 459932 | L100: Hector Ambriz | M100: 1531174 | N100: Hector Ambriz | O100: ambrh001 | P100: ambrihe01 | R100: Hector Ambriz | S100: 29795 | T100: Hector Ambriz | V100: AMBRIZ19840524A | W100: 52005 | X100: 8697 | Y100: Hector Ambriz | Z100: Ambriz, Hector | AA100: L | AB100: R | AC100: Hector Ambriz | AD100: Ambriz, Hector | AE100: 9427 | AI100: 2265 | AK100: Hector Ambriz | AL100: *01t1y* | AM100: Hector Ambriz | AN100: Hector Ambriz | AO100: P | AP100: Ambriz, Hector | AQ100: N
...
